[
  {
    "content_id": 196668,
    "reference_id": 26355,
    "title": "كلمة الله",
    "media_type": "Text",
    "index_reference": "كلمة الله",
    "language": "arb",
    "content": "<h1>كلمة الله، كلمة يهوه، كلمة الرب، كلمة الحق، الكتاب المقدس</h1><h2>التعريف:</h2><p>في الكتاب المقدس، يشير مصطلح &quot;كلمة الله&quot; إلى أي شيء قد تواصل به الله مع الناس. وذلك يشمل الرسائل المنطوقة والمكتوبة. كما يُطلق على يسوع أيضًا &quot;كلمة الله&quot;.</p><ul><li><p>مصطلح &quot;الكتب المقدسة&quot; يعني &quot;الكتابات&quot;. يُستخدم فقط في العهد الجديد ويشير إلى الكتب العبرية، أي العهد القديم. كانت هذه الكتابات رسالة الله التي أمر أُناس بكتابتها حتى يتمكن الشعب في المستقبل من قراءتها.</p></li><li><p>المصطلحات ذات الصلة &quot;كلمة يهوه&quot; و&quot;كلمة الرب&quot; غالبًا ما تشير إلى رسالة محددة من الله أعطيت لنبي أو شخص آخر في الكتاب المقدس.</p></li><li><p>أحيانًا يظهر هذا المصطلح ببساطة كـ &quot;الكلمة&quot; أو &quot;كلمتي&quot; أو &quot;كلمتك&quot; (عند الحديث عن كلمة الله).</p></li><li><p>في العهد الجديد، يُطلق على يسوع &quot;الكلمة&quot; و&quot;كلمة الله&quot;. تعني هذه الألقاب أن يسوع يكشف بالكامل عمن هو الله، لأنه هو الله نفسه.</p></li></ul><p>مصطلح &quot;كلمة الحق&quot; هو طريقة أخرى للإشارة إلى &quot;كلمة الله&quot;، أي رسالته أو تعليمه. وهو لا يشير إلى كلمة واحدة فقط.</p><ul><li><p>تشمل كلمة الله الحق كل ما علّمه الله للشعب عن نفسه، وعن خليقته، وعن خطته للخلاص من خلال يسوع.</p></li><li><p>يؤكد هذا المصطلح على حقيقة أن ما أخبرنا به الله هو صحيح، وأمين، وحقيقي.</p></li></ul><h2>اقتراحات الترجمة:</h2><ul><li><p>اعتمادًا على السياق، يمكن ترجمة هذا المصطلح بطرق أخرى مثل &quot;رسالة يهوه&quot; أو &quot;رسالة الله&quot; أو &quot;تعاليم الله&quot;.</p></li><li><p>قد يكون من الطبيعي في بعض اللغات يكون هذا المصطلح في صيغة الجمع فيكون &quot;كلمات الله&quot; أو &quot;كلمات يهوه&quot;.</p></li><li><p>التعبير &quot;جاءت كلمة يهوه/الرب&quot; يُستخدم غالبًا لتقديم شيء قاله الله لأنبيائه أو لشعبه. يمكن ترجمتها كـ &quot;تحدث يهوه الرب بهذه الرسالة&quot; أو &quot;تحدث يهوه الرب بهذه الكلمات&quot;.</p></li><li><p>يمكن ترجمة مصطلح &quot;الكتاب المقدس&quot; أو &quot;الكتب المقدسة&quot; كـ &quot;الكتابات&quot; أو &quot;الرسالة المكتوبة من الله&quot;. يجب ترجمة هذا المصطلح بشكل مختلف عن ترجمة مصطلح &quot;الكلمة&quot;.</p></li><li><p>عندما يظهر مصطلح &quot;الكلمة&quot; بمفرده ويشير إلى كلمة الله، يمكن ترجمته كـ &quot;الرسالة&quot; أو &quot;كلمة الله&quot; أو &quot;التعاليم&quot;. أيضًا، يمكن النظر في الترجمات البديلة المقترحة أعلاه.</p></li><li><p>عندما يشير الكتاب المقدس إلى يسوع كـ &quot;الكلمة&quot;، يمكن ترجمة هذا المصطلح كـ &quot;الرسالة&quot; أو &quot;الحقيقة&quot;.</p></li><li><p>يمكن ترجمة &quot;كلمة الحق&quot; كـ &quot;رسالة الله الحقيقية&quot; أو &quot;كلمة الله، التي هي حقيقية&quot;.</p></li><li><p>من المهم أن تتضمن ترجمة هذا المصطلح معنى كونه حقيقيًا.</p></li></ul><p>(انظر أيضًا: <span data-bnType=\"resourceReference\" data-resourceId=\"26129\" data-resourceType=\"UWTranslationWords\">نبي</span>, <span data-bnType=\"resourceReference\" data-resourceId=\"UnfoldingWord_TranslatorWords_true\" data-resourceType=\"UWTranslationWords\">صادق</span>, <span data-bnType=\"resourceReference\" data-resourceId=\"26360\" data-resourceType=\"UWTranslationWords\">يهوه</span>)</p><h2>مراجع الكتاب المقدس:</h2><ul><li><p><a href=\"https://ref.ly/Gen15:1\">تكوين 15: 1</a></p></li><li><p><a href=\"https://ref.ly/1Kgs13:1\">1 ملوك 13: 1</a></p></li><li><p><a href=\"https://ref.ly/Jer36:1-Jer36:3\">إرميا 36: 1–3</a></p></li><li><p><a href=\"https://ref.ly/Luke8:11\">لوقا 8: 11</a></p></li><li><p><a href=\"https://ref.ly/John5:39\">يوحنا 5: 39</a></p></li><li><p><a href=\"https://ref.ly/Acts6:2\">أعمال 6: 2</a></p></li><li><p><a href=\"https://ref.ly/Acts12:24\">أعمال 12: 24</a></p></li><li><p><a href=\"https://ref.ly/Rom1:2\">رومية 1: 2</a></p></li><li><p><a href=\"https://ref.ly/2Cor6:7\">2 كورنثوس 6: 7</a></p></li><li><p><a href=\"https://ref.ly/Eph1:13\">أفسس 1: 13</a></p></li><li><p><a href=\"https://ref.ly/2Tim3:16\">2 تيموثاوس 3: 16</a></p></li><li><p><a href=\"https://ref.ly/Jas1:18\">يعقوب 1: 18</a></p></li><li><p><a href=\"https://ref.ly/Jas2:8-Jas2:9\">يعقوب 2: 8–9</a></p></li></ul><h2>أمثلة من قصص الكتاب المقدس:</h2><ul><li><p><strong>25: 7</strong> في <strong>كلمة الله</strong> يأمر الرب شعبه، &quot;اعبدوا الرب إلهكم فقط واخدموه هو فقط&quot;.</p></li><li><p><strong>33: 6</strong> فشرح يسوع، &quot;البذرة هي <strong>كلمة الله</strong>&quot;.</p></li><li><p><strong>42: 3</strong> ثم شرح يسوع لهم ما تقوله <strong>كلمة الله</strong> عن المسيا.</p></li><li><p><strong>42: 7</strong> قال يسوع، &quot;قلت لكم أن كل شيء مكتوب عني في <strong>كلمة الله</strong> يجب أن يتم.&quot; ثم فتح عقولهم لكي يفهموا <strong>كلمة الله</strong>.</p></li><li><p><strong>45: 10</strong> استخدم فيلبس أيضًا <strong>كتب مقدسة</strong> أخرى ليخبره بالأخبار السارة الخاصة بيسوع.</p></li><li><p><strong>48: 12</strong> لكن يسوع هو أعظم نبي على الإطلاق. هو <strong>كلمة الله</strong>.</p></li><li><p><strong>49: 18</strong> الله يخبرك أن تُصلّي، وأن تدرس <strong>كلمته</strong>، وأن تعبده مع المسيحيين الآخرين، وأن تخبر الآخرين بما فعله من أجلك.</p></li></ul><h2>بيانات الكلمة:</h2><ul><li><p>قاموس سترونج: H0561, H0565, H1697, H3068, G30560, G44870</p></li></ul>",
    "associations": {
      "passage": [
        {
          "start_ref": "01015001",
          "start_ref_usfm": "GEN 15:1",
          "end_ref": "01015001",
          "end_ref_usfm": "GEN 15:1"
        },
        {
          "start_ref": "02009020",
          "start_ref_usfm": "EXO 9:20",
          "end_ref": "02009020",
          "end_ref_usfm": "EXO 9:20"
        },
        {
          "start_ref": "02009021",
          "start_ref_usfm": "EXO 9:21",
          "end_ref": "02009021",
          "end_ref_usfm": "EXO 9:21"
        },
        {
          "start_ref": "02024003",
          "start_ref_usfm": "EXO 24:3",
          "end_ref": "02024003",
          "end_ref_usfm": "EXO 24:3"
        },
        {
          "start_ref": "02024004",
          "start_ref_usfm": "EXO 24:4",
          "end_ref": "02024004",
          "end_ref_usfm": "EXO 24:4"
        },
        {
          "start_ref": "11013001",
          "start_ref_usfm": "1KI 13:1",
          "end_ref": "11013001",
          "end_ref_usfm": "1KI 13:1"
        },
        {
          "start_ref": "32001001",
          "start_ref_usfm": "JON 1:1",
          "end_ref": "32001001",
          "end_ref_usfm": "JON 1:1"
        },
        {
          "start_ref": "32003001",
          "start_ref_usfm": "JON 3:1",
          "end_ref": "32003001",
          "end_ref_usfm": "JON 3:1"
        },
        {
          "start_ref": "32003003",
          "start_ref_usfm": "JON 3:3",
          "end_ref": "32003003",
          "end_ref_usfm": "JON 3:3"
        },
        {
          "start_ref": "40015006",
          "start_ref_usfm": "MAT 15:6",
          "end_ref": "40015006",
          "end_ref_usfm": "MAT 15:6"
        },
        {
          "start_ref": "40021042",
          "start_ref_usfm": "MAT 21:42",
          "end_ref": "40021042",
          "end_ref_usfm": "MAT 21:42"
        },
        {
          "start_ref": "40022029",
          "start_ref_usfm": "MAT 22:29",
          "end_ref": "40022029",
          "end_ref_usfm": "MAT 22:29"
        },
        {
          "start_ref": "40026054",
          "start_ref_usfm": "MAT 26:54",
          "end_ref": "40026054",
          "end_ref_usfm": "MAT 26:54"
        },
        {
          "start_ref": "40026056",
          "start_ref_usfm": "MAT 26:56",
          "end_ref": "40026056",
          "end_ref_usfm": "MAT 26:56"
        },
        {
          "start_ref": "41004015",
          "start_ref_usfm": "MRK 4:15",
          "end_ref": "41004015",
          "end_ref_usfm": "MRK 4:15"
        },
        {
          "start_ref": "41004016",
          "start_ref_usfm": "MRK 4:16",
          "end_ref": "41004016",
          "end_ref_usfm": "MRK 4:16"
        },
        {
          "start_ref": "41004017",
          "start_ref_usfm": "MRK 4:17",
          "end_ref": "41004017",
          "end_ref_usfm": "MRK 4:17"
        },
        {
          "start_ref": "41004018",
          "start_ref_usfm": "MRK 4:18",
          "end_ref": "41004018",
          "end_ref_usfm": "MRK 4:18"
        },
        {
          "start_ref": "41004019",
          "start_ref_usfm": "MRK 4:19",
          "end_ref": "41004019",
          "end_ref_usfm": "MRK 4:19"
        },
        {
          "start_ref": "41004020",
          "start_ref_usfm": "MRK 4:20",
          "end_ref": "41004020",
          "end_ref_usfm": "MRK 4:20"
        },
        {
          "start_ref": "41004033",
          "start_ref_usfm": "MRK 4:33",
          "end_ref": "41004033",
          "end_ref_usfm": "MRK 4:33"
        },
        {
          "start_ref": "41007013",
          "start_ref_usfm": "MRK 7:13",
          "end_ref": "41007013",
          "end_ref_usfm": "MRK 7:13"
        },
        {
          "start_ref": "41012010",
          "start_ref_usfm": "MRK 12:10",
          "end_ref": "41012010",
          "end_ref_usfm": "MRK 12:10"
        },
        {
          "start_ref": "41012024",
          "start_ref_usfm": "MRK 12:24",
          "end_ref": "41012024",
          "end_ref_usfm": "MRK 12:24"
        },
        {
          "start_ref": "41013031",
          "start_ref_usfm": "MRK 13:31",
          "end_ref": "41013031",
          "end_ref_usfm": "MRK 13:31"
        },
        {
          "start_ref": "41014049",
          "start_ref_usfm": "MRK 14:49",
          "end_ref": "41014049",
          "end_ref_usfm": "MRK 14:49"
        },
        {
          "start_ref": "42001002",
          "start_ref_usfm": "LUK 1:2",
          "end_ref": "42001002",
          "end_ref_usfm": "LUK 1:2"
        },
        {
          "start_ref": "42003002",
          "start_ref_usfm": "LUK 3:2",
          "end_ref": "42003002",
          "end_ref_usfm": "LUK 3:2"
        },
        {
          "start_ref": "42004021",
          "start_ref_usfm": "LUK 4:21",
          "end_ref": "42004021",
          "end_ref_usfm": "LUK 4:21"
        },
        {
          "start_ref": "42005001",
          "start_ref_usfm": "LUK 5:1",
          "end_ref": "42005001",
          "end_ref_usfm": "LUK 5:1"
        },
        {
          "start_ref": "42008011",
          "start_ref_usfm": "LUK 8:11",
          "end_ref": "42008011",
          "end_ref_usfm": "LUK 8:11"
        },
        {
          "start_ref": "42008012",
          "start_ref_usfm": "LUK 8:12",
          "end_ref": "42008012",
          "end_ref_usfm": "LUK 8:12"
        },
        {
          "start_ref": "42008013",
          "start_ref_usfm": "LUK 8:13",
          "end_ref": "42008013",
          "end_ref_usfm": "LUK 8:13"
        },
        {
          "start_ref": "42008015",
          "start_ref_usfm": "LUK 8:15",
          "end_ref": "42008015",
          "end_ref_usfm": "LUK 8:15"
        },
        {
          "start_ref": "42008021",
          "start_ref_usfm": "LUK 8:21",
          "end_ref": "42008021",
          "end_ref_usfm": "LUK 8:21"
        },
        {
          "start_ref": "42011028",
          "start_ref_usfm": "LUK 11:28",
          "end_ref": "42011028",
          "end_ref_usfm": "LUK 11:28"
        },
        {
          "start_ref": "42021033",
          "start_ref_usfm": "LUK 21:33",
          "end_ref": "42021033",
          "end_ref_usfm": "LUK 21:33"
        },
        {
          "start_ref": "42024027",
          "start_ref_usfm": "LUK 24:27",
          "end_ref": "42024027",
          "end_ref_usfm": "LUK 24:27"
        },
        {
          "start_ref": "42024032",
          "start_ref_usfm": "LUK 24:32",
          "end_ref": "42024032",
          "end_ref_usfm": "LUK 24:32"
        },
        {
          "start_ref": "42024045",
          "start_ref_usfm": "LUK 24:45",
          "end_ref": "42024045",
          "end_ref_usfm": "LUK 24:45"
        },
        {
          "start_ref": "43001001",
          "start_ref_usfm": "JHN 1:1",
          "end_ref": "43001001",
          "end_ref_usfm": "JHN 1:1"
        },
        {
          "start_ref": "43001014",
          "start_ref_usfm": "JHN 1:14",
          "end_ref": "43001014",
          "end_ref_usfm": "JHN 1:14"
        },
        {
          "start_ref": "43002022",
          "start_ref_usfm": "JHN 2:22",
          "end_ref": "43002022",
          "end_ref_usfm": "JHN 2:22"
        },
        {
          "start_ref": "43003034",
          "start_ref_usfm": "JHN 3:34",
          "end_ref": "43003034",
          "end_ref_usfm": "JHN 3:34"
        },
        {
          "start_ref": "43005024",
          "start_ref_usfm": "JHN 5:24",
          "end_ref": "43005024",
          "end_ref_usfm": "JHN 5:24"
        },
        {
          "start_ref": "43005038",
          "start_ref_usfm": "JHN 5:38",
          "end_ref": "43005038",
          "end_ref_usfm": "JHN 5:38"
        },
        {
          "start_ref": "43005039",
          "start_ref_usfm": "JHN 5:39",
          "end_ref": "43005039",
          "end_ref_usfm": "JHN 5:39"
        },
        {
          "start_ref": "43007015",
          "start_ref_usfm": "JHN 7:15",
          "end_ref": "43007015",
          "end_ref_usfm": "JHN 7:15"
        },
        {
          "start_ref": "43007038",
          "start_ref_usfm": "JHN 7:38",
          "end_ref": "43007038",
          "end_ref_usfm": "JHN 7:38"
        },
        {
          "start_ref": "43007042",
          "start_ref_usfm": "JHN 7:42",
          "end_ref": "43007042",
          "end_ref_usfm": "JHN 7:42"
        },
        {
          "start_ref": "43008031",
          "start_ref_usfm": "JHN 8:31",
          "end_ref": "43008031",
          "end_ref_usfm": "JHN 8:31"
        },
        {
          "start_ref": "43008047",
          "start_ref_usfm": "JHN 8:47",
          "end_ref": "43008047",
          "end_ref_usfm": "JHN 8:47"
        },
        {
          "start_ref": "43008055",
          "start_ref_usfm": "JHN 8:55",
          "end_ref": "43008055",
          "end_ref_usfm": "JHN 8:55"
        },
        {
          "start_ref": "43010035",
          "start_ref_usfm": "JHN 10:35",
          "end_ref": "43010035",
          "end_ref_usfm": "JHN 10:35"
        },
        {
          "start_ref": "43012048",
          "start_ref_usfm": "JHN 12:48",
          "end_ref": "43012048",
          "end_ref_usfm": "JHN 12:48"
        },
        {
          "start_ref": "43013018",
          "start_ref_usfm": "JHN 13:18",
          "end_ref": "43013018",
          "end_ref_usfm": "JHN 13:18"
        },
        {
          "start_ref": "43014023",
          "start_ref_usfm": "JHN 14:23",
          "end_ref": "43014023",
          "end_ref_usfm": "JHN 14:23"
        },
        {
          "start_ref": "43014024",
          "start_ref_usfm": "JHN 14:24",
          "end_ref": "43014024",
          "end_ref_usfm": "JHN 14:24"
        },
        {
          "start_ref": "43015003",
          "start_ref_usfm": "JHN 15:3",
          "end_ref": "43015003",
          "end_ref_usfm": "JHN 15:3"
        },
        {
          "start_ref": "43015007",
          "start_ref_usfm": "JHN 15:7",
          "end_ref": "43015007",
          "end_ref_usfm": "JHN 15:7"
        },
        {
          "start_ref": "43015020",
          "start_ref_usfm": "JHN 15:20",
          "end_ref": "43015020",
          "end_ref_usfm": "JHN 15:20"
        },
        {
          "start_ref": "43015025",
          "start_ref_usfm": "JHN 15:25",
          "end_ref": "43015025",
          "end_ref_usfm": "JHN 15:25"
        },
        {
          "start_ref": "43017006",
          "start_ref_usfm": "JHN 17:6",
          "end_ref": "43017006",
          "end_ref_usfm": "JHN 17:6"
        },
        {
          "start_ref": "43017012",
          "start_ref_usfm": "JHN 17:12",
          "end_ref": "43017012",
          "end_ref_usfm": "JHN 17:12"
        },
        {
          "start_ref": "43017014",
          "start_ref_usfm": "JHN 17:14",
          "end_ref": "43017014",
          "end_ref_usfm": "JHN 17:14"
        },
        {
          "start_ref": "43017017",
          "start_ref_usfm": "JHN 17:17",
          "end_ref": "43017017",
          "end_ref_usfm": "JHN 17:17"
        },
        {
          "start_ref": "43018009",
          "start_ref_usfm": "JHN 18:9",
          "end_ref": "43018009",
          "end_ref_usfm": "JHN 18:9"
        },
        {
          "start_ref": "43018032",
          "start_ref_usfm": "JHN 18:32",
          "end_ref": "43018032",
          "end_ref_usfm": "JHN 18:32"
        },
        {
          "start_ref": "43019024",
          "start_ref_usfm": "JHN 19:24",
          "end_ref": "43019024",
          "end_ref_usfm": "JHN 19:24"
        },
        {
          "start_ref": "43019028",
          "start_ref_usfm": "JHN 19:28",
          "end_ref": "43019028",
          "end_ref_usfm": "JHN 19:28"
        },
        {
          "start_ref": "43019036",
          "start_ref_usfm": "JHN 19:36",
          "end_ref": "43019036",
          "end_ref_usfm": "JHN 19:36"
        },
        {
          "start_ref": "43019037",
          "start_ref_usfm": "JHN 19:37",
          "end_ref": "43019037",
          "end_ref_usfm": "JHN 19:37"
        },
        {
          "start_ref": "43020009",
          "start_ref_usfm": "JHN 20:9",
          "end_ref": "43020009",
          "end_ref_usfm": "JHN 20:9"
        },
        {
          "start_ref": "44001016",
          "start_ref_usfm": "ACT 1:16",
          "end_ref": "44001016",
          "end_ref_usfm": "ACT 1:16"
        },
        {
          "start_ref": "44004029",
          "start_ref_usfm": "ACT 4:29",
          "end_ref": "44004029",
          "end_ref_usfm": "ACT 4:29"
        },
        {
          "start_ref": "44004031",
          "start_ref_usfm": "ACT 4:31",
          "end_ref": "44004031",
          "end_ref_usfm": "ACT 4:31"
        },
        {
          "start_ref": "44005020",
          "start_ref_usfm": "ACT 5:20",
          "end_ref": "44005020",
          "end_ref_usfm": "ACT 5:20"
        },
        {
          "start_ref": "44006002",
          "start_ref_usfm": "ACT 6:2",
          "end_ref": "44006002",
          "end_ref_usfm": "ACT 6:2"
        },
        {
          "start_ref": "44006004",
          "start_ref_usfm": "ACT 6:4",
          "end_ref": "44006004",
          "end_ref_usfm": "ACT 6:4"
        },
        {
          "start_ref": "44006007",
          "start_ref_usfm": "ACT 6:7",
          "end_ref": "44006007",
          "end_ref_usfm": "ACT 6:7"
        },
        {
          "start_ref": "44008004",
          "start_ref_usfm": "ACT 8:4",
          "end_ref": "44008004",
          "end_ref_usfm": "ACT 8:4"
        },
        {
          "start_ref": "44008014",
          "start_ref_usfm": "ACT 8:14",
          "end_ref": "44008014",
          "end_ref_usfm": "ACT 8:14"
        },
        {
          "start_ref": "44008025",
          "start_ref_usfm": "ACT 8:25",
          "end_ref": "44008025",
          "end_ref_usfm": "ACT 8:25"
        },
        {
          "start_ref": "44008032",
          "start_ref_usfm": "ACT 8:32",
          "end_ref": "44008032",
          "end_ref_usfm": "ACT 8:32"
        },
        {
          "start_ref": "44008035",
          "start_ref_usfm": "ACT 8:35",
          "end_ref": "44008035",
          "end_ref_usfm": "ACT 8:35"
        },
        {
          "start_ref": "44010036",
          "start_ref_usfm": "ACT 10:36",
          "end_ref": "44010036",
          "end_ref_usfm": "ACT 10:36"
        },
        {
          "start_ref": "44011001",
          "start_ref_usfm": "ACT 11:1",
          "end_ref": "44011001",
          "end_ref_usfm": "ACT 11:1"
        },
        {
          "start_ref": "44011019",
          "start_ref_usfm": "ACT 11:19",
          "end_ref": "44011019",
          "end_ref_usfm": "ACT 11:19"
        },
        {
          "start_ref": "44012024",
          "start_ref_usfm": "ACT 12:24",
          "end_ref": "44012024",
          "end_ref_usfm": "ACT 12:24"
        },
        {
          "start_ref": "44013005",
          "start_ref_usfm": "ACT 13:5",
          "end_ref": "44013005",
          "end_ref_usfm": "ACT 13:5"
        },
        {
          "start_ref": "44013007",
          "start_ref_usfm": "ACT 13:7",
          "end_ref": "44013007",
          "end_ref_usfm": "ACT 13:7"
        },
        {
          "start_ref": "44013044",
          "start_ref_usfm": "ACT 13:44",
          "end_ref": "44013044",
          "end_ref_usfm": "ACT 13:44"
        },
        {
          "start_ref": "44013046",
          "start_ref_usfm": "ACT 13:46",
          "end_ref": "44013046",
          "end_ref_usfm": "ACT 13:46"
        },
        {
          "start_ref": "44013048",
          "start_ref_usfm": "ACT 13:48",
          "end_ref": "44013048",
          "end_ref_usfm": "ACT 13:48"
        },
        {
          "start_ref": "44013049",
          "start_ref_usfm": "ACT 13:49",
          "end_ref": "44013049",
          "end_ref_usfm": "ACT 13:49"
        },
        {
          "start_ref": "44014003",
          "start_ref_usfm": "ACT 14:3",
          "end_ref": "44014003",
          "end_ref_usfm": "ACT 14:3"
        },
        {
          "start_ref": "44014025",
          "start_ref_usfm": "ACT 14:25",
          "end_ref": "44014025",
          "end_ref_usfm": "ACT 14:25"
        },
        {
          "start_ref": "44015035",
          "start_ref_usfm": "ACT 15:35",
          "end_ref": "44015035",
          "end_ref_usfm": "ACT 15:35"
        },
        {
          "start_ref": "44015036",
          "start_ref_usfm": "ACT 15:36",
          "end_ref": "44015036",
          "end_ref_usfm": "ACT 15:36"
        },
        {
          "start_ref": "44016006",
          "start_ref_usfm": "ACT 16:6",
          "end_ref": "44016006",
          "end_ref_usfm": "ACT 16:6"
        },
        {
          "start_ref": "44016032",
          "start_ref_usfm": "ACT 16:32",
          "end_ref": "44016032",
          "end_ref_usfm": "ACT 16:32"
        },
        {
          "start_ref": "44017002",
          "start_ref_usfm": "ACT 17:2",
          "end_ref": "44017002",
          "end_ref_usfm": "ACT 17:2"
        },
        {
          "start_ref": "44017011",
          "start_ref_usfm": "ACT 17:11",
          "end_ref": "44017011",
          "end_ref_usfm": "ACT 17:11"
        },
        {
          "start_ref": "44017013",
          "start_ref_usfm": "ACT 17:13",
          "end_ref": "44017013",
          "end_ref_usfm": "ACT 17:13"
        },
        {
          "start_ref": "44018005",
          "start_ref_usfm": "ACT 18:5",
          "end_ref": "44018005",
          "end_ref_usfm": "ACT 18:5"
        },
        {
          "start_ref": "44018011",
          "start_ref_usfm": "ACT 18:11",
          "end_ref": "44018011",
          "end_ref_usfm": "ACT 18:11"
        },
        {
          "start_ref": "44018024",
          "start_ref_usfm": "ACT 18:24",
          "end_ref": "44018024",
          "end_ref_usfm": "ACT 18:24"
        },
        {
          "start_ref": "44018028",
          "start_ref_usfm": "ACT 18:28",
          "end_ref": "44018028",
          "end_ref_usfm": "ACT 18:28"
        },
        {
          "start_ref": "44019010",
          "start_ref_usfm": "ACT 19:10",
          "end_ref": "44019010",
          "end_ref_usfm": "ACT 19:10"
        },
        {
          "start_ref": "44019020",
          "start_ref_usfm": "ACT 19:20",
          "end_ref": "44019020",
          "end_ref_usfm": "ACT 19:20"
        },
        {
          "start_ref": "45001002",
          "start_ref_usfm": "ROM 1:2",
          "end_ref": "45001002",
          "end_ref_usfm": "ROM 1:2"
        },
        {
          "start_ref": "45004003",
          "start_ref_usfm": "ROM 4:3",
          "end_ref": "45004003",
          "end_ref_usfm": "ROM 4:3"
        },
        {
          "start_ref": "45009006",
          "start_ref_usfm": "ROM 9:6",
          "end_ref": "45009006",
          "end_ref_usfm": "ROM 9:6"
        },
        {
          "start_ref": "45009017",
          "start_ref_usfm": "ROM 9:17",
          "end_ref": "45009017",
          "end_ref_usfm": "ROM 9:17"
        },
        {
          "start_ref": "45010011",
          "start_ref_usfm": "ROM 10:11",
          "end_ref": "45010011",
          "end_ref_usfm": "ROM 10:11"
        },
        {
          "start_ref": "45011002",
          "start_ref_usfm": "ROM 11:2",
          "end_ref": "45011002",
          "end_ref_usfm": "ROM 11:2"
        },
        {
          "start_ref": "45015004",
          "start_ref_usfm": "ROM 15:4",
          "end_ref": "45015004",
          "end_ref_usfm": "ROM 15:4"
        },
        {
          "start_ref": "45016026",
          "start_ref_usfm": "ROM 16:26",
          "end_ref": "45016026",
          "end_ref_usfm": "ROM 16:26"
        },
        {
          "start_ref": "46014036",
          "start_ref_usfm": "1CO 14:36",
          "end_ref": "46014036",
          "end_ref_usfm": "1CO 14:36"
        },
        {
          "start_ref": "46015003",
          "start_ref_usfm": "1CO 15:3",
          "end_ref": "46015003",
          "end_ref_usfm": "1CO 15:3"
        },
        {
          "start_ref": "46015004",
          "start_ref_usfm": "1CO 15:4",
          "end_ref": "46015004",
          "end_ref_usfm": "1CO 15:4"
        },
        {
          "start_ref": "47002017",
          "start_ref_usfm": "2CO 2:17",
          "end_ref": "47002017",
          "end_ref_usfm": "2CO 2:17"
        },
        {
          "start_ref": "47004002",
          "start_ref_usfm": "2CO 4:2",
          "end_ref": "47004002",
          "end_ref_usfm": "2CO 4:2"
        },
        {
          "start_ref": "47006007",
          "start_ref_usfm": "2CO 6:7",
          "end_ref": "47006007",
          "end_ref_usfm": "2CO 6:7"
        },
        {
          "start_ref": "49001013",
          "start_ref_usfm": "EPH 1:13",
          "end_ref": "49001013",
          "end_ref_usfm": "EPH 1:13"
        },
        {
          "start_ref": "49005026",
          "start_ref_usfm": "EPH 5:26",
          "end_ref": "49005026",
          "end_ref_usfm": "EPH 5:26"
        },
        {
          "start_ref": "49006017",
          "start_ref_usfm": "EPH 6:17",
          "end_ref": "49006017",
          "end_ref_usfm": "EPH 6:17"
        },
        {
          "start_ref": "50001014",
          "start_ref_usfm": "PHP 1:14",
          "end_ref": "50001014",
          "end_ref_usfm": "PHP 1:14"
        },
        {
          "start_ref": "51001025",
          "start_ref_usfm": "COL 1:25",
          "end_ref": "51001025",
          "end_ref_usfm": "COL 1:25"
        },
        {
          "start_ref": "51003016",
          "start_ref_usfm": "COL 3:16",
          "end_ref": "51003016",
          "end_ref_usfm": "COL 3:16"
        },
        {
          "start_ref": "51004003",
          "start_ref_usfm": "COL 4:3",
          "end_ref": "51004003",
          "end_ref_usfm": "COL 4:3"
        },
        {
          "start_ref": "52001008",
          "start_ref_usfm": "1TH 1:8",
          "end_ref": "52001008",
          "end_ref_usfm": "1TH 1:8"
        },
        {
          "start_ref": "52002013",
          "start_ref_usfm": "1TH 2:13",
          "end_ref": "52002013",
          "end_ref_usfm": "1TH 2:13"
        },
        {
          "start_ref": "52004015",
          "start_ref_usfm": "1TH 4:15",
          "end_ref": "52004015",
          "end_ref_usfm": "1TH 4:15"
        },
        {
          "start_ref": "53003001",
          "start_ref_usfm": "2TH 3:1",
          "end_ref": "53003001",
          "end_ref_usfm": "2TH 3:1"
        },
        {
          "start_ref": "54004005",
          "start_ref_usfm": "1TI 4:5",
          "end_ref": "54004005",
          "end_ref_usfm": "1TI 4:5"
        },
        {
          "start_ref": "54005018",
          "start_ref_usfm": "1TI 5:18",
          "end_ref": "54005018",
          "end_ref_usfm": "1TI 5:18"
        },
        {
          "start_ref": "55002009",
          "start_ref_usfm": "2TI 2:9",
          "end_ref": "55002009",
          "end_ref_usfm": "2TI 2:9"
        },
        {
          "start_ref": "55002015",
          "start_ref_usfm": "2TI 2:15",
          "end_ref": "55002015",
          "end_ref_usfm": "2TI 2:15"
        },
        {
          "start_ref": "55003015",
          "start_ref_usfm": "2TI 3:15",
          "end_ref": "55003015",
          "end_ref_usfm": "2TI 3:15"
        },
        {
          "start_ref": "55003016",
          "start_ref_usfm": "2TI 3:16",
          "end_ref": "55003016",
          "end_ref_usfm": "2TI 3:16"
        },
        {
          "start_ref": "55004002",
          "start_ref_usfm": "2TI 4:2",
          "end_ref": "55004002",
          "end_ref_usfm": "2TI 4:2"
        },
        {
          "start_ref": "56001003",
          "start_ref_usfm": "TIT 1:3",
          "end_ref": "56001003",
          "end_ref_usfm": "TIT 1:3"
        },
        {
          "start_ref": "56002005",
          "start_ref_usfm": "TIT 2:5",
          "end_ref": "56002005",
          "end_ref_usfm": "TIT 2:5"
        },
        {
          "start_ref": "58004012",
          "start_ref_usfm": "HEB 4:12",
          "end_ref": "58004012",
          "end_ref_usfm": "HEB 4:12"
        },
        {
          "start_ref": "58006005",
          "start_ref_usfm": "HEB 6:5",
          "end_ref": "58006005",
          "end_ref_usfm": "HEB 6:5"
        },
        {
          "start_ref": "58013007",
          "start_ref_usfm": "HEB 13:7",
          "end_ref": "58013007",
          "end_ref_usfm": "HEB 13:7"
        },
        {
          "start_ref": "59001018",
          "start_ref_usfm": "JAS 1:18",
          "end_ref": "59001018",
          "end_ref_usfm": "JAS 1:18"
        },
        {
          "start_ref": "59001021",
          "start_ref_usfm": "JAS 1:21",
          "end_ref": "59001021",
          "end_ref_usfm": "JAS 1:21"
        },
        {
          "start_ref": "59001022",
          "start_ref_usfm": "JAS 1:22",
          "end_ref": "59001022",
          "end_ref_usfm": "JAS 1:22"
        },
        {
          "start_ref": "59001023",
          "start_ref_usfm": "JAS 1:23",
          "end_ref": "59001023",
          "end_ref_usfm": "JAS 1:23"
        },
        {
          "start_ref": "59002008",
          "start_ref_usfm": "JAS 2:8",
          "end_ref": "59002008",
          "end_ref_usfm": "JAS 2:8"
        },
        {
          "start_ref": "59002023",
          "start_ref_usfm": "JAS 2:23",
          "end_ref": "59002023",
          "end_ref_usfm": "JAS 2:23"
        },
        {
          "start_ref": "59004005",
          "start_ref_usfm": "JAS 4:5",
          "end_ref": "59004005",
          "end_ref_usfm": "JAS 4:5"
        },
        {
          "start_ref": "60001023",
          "start_ref_usfm": "1PE 1:23",
          "end_ref": "60001023",
          "end_ref_usfm": "1PE 1:23"
        },
        {
          "start_ref": "60001025",
          "start_ref_usfm": "1PE 1:25",
          "end_ref": "60001025",
          "end_ref_usfm": "1PE 1:25"
        },
        {
          "start_ref": "60002006",
          "start_ref_usfm": "1PE 2:6",
          "end_ref": "60002006",
          "end_ref_usfm": "1PE 2:6"
        },
        {
          "start_ref": "60002008",
          "start_ref_usfm": "1PE 2:8",
          "end_ref": "60002008",
          "end_ref_usfm": "1PE 2:8"
        },
        {
          "start_ref": "60003001",
          "start_ref_usfm": "1PE 3:1",
          "end_ref": "60003001",
          "end_ref_usfm": "1PE 3:1"
        },
        {
          "start_ref": "61001020",
          "start_ref_usfm": "2PE 1:20",
          "end_ref": "61001020",
          "end_ref_usfm": "2PE 1:20"
        },
        {
          "start_ref": "61003016",
          "start_ref_usfm": "2PE 3:16",
          "end_ref": "61003016",
          "end_ref_usfm": "2PE 3:16"
        },
        {
          "start_ref": "62002014",
          "start_ref_usfm": "1JN 2:14",
          "end_ref": "62002014",
          "end_ref_usfm": "1JN 2:14"
        },
        {
          "start_ref": "66001002",
          "start_ref_usfm": "REV 1:2",
          "end_ref": "66001002",
          "end_ref_usfm": "REV 1:2"
        },
        {
          "start_ref": "66001009",
          "start_ref_usfm": "REV 1:9",
          "end_ref": "66001009",
          "end_ref_usfm": "REV 1:9"
        },
        {
          "start_ref": "66003008",
          "start_ref_usfm": "REV 3:8",
          "end_ref": "66003008",
          "end_ref_usfm": "REV 3:8"
        },
        {
          "start_ref": "66003010",
          "start_ref_usfm": "REV 3:10",
          "end_ref": "66003010",
          "end_ref_usfm": "REV 3:10"
        },
        {
          "start_ref": "66006009",
          "start_ref_usfm": "REV 6:9",
          "end_ref": "66006009",
          "end_ref_usfm": "REV 6:9"
        },
        {
          "start_ref": "66019013",
          "start_ref_usfm": "REV 19:13",
          "end_ref": "66019013",
          "end_ref_usfm": "REV 19:13"
        },
        {
          "start_ref": "66020004",
          "start_ref_usfm": "REV 20:4",
          "end_ref": "66020004",
          "end_ref_usfm": "REV 20:4"
        },
        {
          "start_ref": "24036001",
          "start_ref_usfm": "JER 36:1",
          "end_ref": "24036003",
          "end_ref_usfm": "JER 36:3"
        },
        {
          "start_ref": "59002008",
          "start_ref_usfm": "JAS 2:8",
          "end_ref": "59002009",
          "end_ref_usfm": "JAS 2:9"
        }
      ],
      "resource": [
        {
          "reference_id": 26129,
          "content_id": 196486,
          "resource_code": "UWTranslationWords",
          "label": "نبي",
          "language": "arb"
        },
        {
          "reference_id": 26360,
          "content_id": 196673,
          "resource_code": "UWTranslationWords",
          "label": "يهوه",
          "language": "arb"
        }
      ]
    }
  }
]