[
  {
    "content_id": 336329,
    "reference_id": 26146,
    "version": "1.0.0",
    "title": "Apagar",
    "media_type": "Text",
    "index_reference": "apagar",
    "language": "spa",
    "content": "<h1>apagar, apagado, inextinguible</h1><h2>Definición:</h2><p>El término &quot;apagar&quot; significa extinguir o detener algo que exige ser satisfecho.</p><ul><li><p>Este término se usa generalmente en el contexto de saciar la sed y significa dejar de tener sed bebiendo algo.</p></li><li><p>También se puede usar para referirse a apagar un incendio.</p></li><li><p>Tanto la sed como el fuego se apagan con agua.</p></li><li><p>Pablo usa el término &quot;apagar&quot; de manera figurada cuando instruye a los creyentes a no &quot;apagar al Espíritu Santo&quot;. Esto significa no desalentar a las personas de permitir que el Espíritu Santo produzca sus frutos y dones en ellos. Apagar al Espíritu Santo significa impedir que el Espíritu Santo manifieste libremente su poder y obra en las personas.</p></li></ul><p>(Véase también: <span data-bnType=\"resourceReference\" data-resourceId=\"25760\" data-resourceType=\"UWTranslationWords\">fruto</span>, <span data-bnType=\"resourceReference\" data-resourceId=\"UnfoldingWord_TranslatorWords_gift\" data-resourceType=\"UWTranslationWords\">don</span>, <span data-bnType=\"resourceReference\" data-resourceId=\"25844\" data-resourceType=\"UWTranslationWords\">Espíritu Santo</span>).</p><h2>Referencias Bíblicas:</h2><ul><li><p><a href=\"https://ref.ly/1Thess5:19\">1 Tesalonicenses 5:19</a></p></li><li><p><a href=\"https://ref.ly/Ezek20:47\">Ezequiel 20:47</a></p></li><li><p><a href=\"https://ref.ly/Isa1:31\">Isaías 1:31</a></p></li><li><p><a href=\"https://ref.ly/Jer21:12\">Jeremías 21:12</a></p></li></ul><h2>Datos de la palabra:</h2><ul><li><p>Strong’s: H1846, H3518, H7665, G07620, G45700</p></li></ul>",
    "associations": {
      "passage": [
        {
          "start_ref": "23001031",
          "start_ref_usfm": "ISA 1:31",
          "end_ref": "23001031",
          "end_ref_usfm": "ISA 1:31"
        },
        {
          "start_ref": "24021012",
          "start_ref_usfm": "JER 21:12",
          "end_ref": "24021012",
          "end_ref_usfm": "JER 21:12"
        },
        {
          "start_ref": "26020047",
          "start_ref_usfm": "EZK 20:47",
          "end_ref": "26020047",
          "end_ref_usfm": "EZK 20:47"
        },
        {
          "start_ref": "40012020",
          "start_ref_usfm": "MAT 12:20",
          "end_ref": "40012020",
          "end_ref_usfm": "MAT 12:20"
        },
        {
          "start_ref": "41009048",
          "start_ref_usfm": "MRK 9:48",
          "end_ref": "41009048",
          "end_ref_usfm": "MRK 9:48"
        },
        {
          "start_ref": "49006016",
          "start_ref_usfm": "EPH 6:16",
          "end_ref": "49006016",
          "end_ref_usfm": "EPH 6:16"
        },
        {
          "start_ref": "52005019",
          "start_ref_usfm": "1TH 5:19",
          "end_ref": "52005019",
          "end_ref_usfm": "1TH 5:19"
        },
        {
          "start_ref": "58011034",
          "start_ref_usfm": "HEB 11:34",
          "end_ref": "58011034",
          "end_ref_usfm": "HEB 11:34"
        }
      ],
      "resource": [
        {
          "reference_id": 25760,
          "content_id": 335602,
          "resource_code": "UWTranslationWords",
          "label": "Fruta",
          "language": "spa"
        },
        {
          "reference_id": 25844,
          "content_id": 335611,
          "resource_code": "UWTranslationWords",
          "label": "Espíritu Santo",
          "language": "spa"
        }
      ]
    }
  }
]