[
  {
    "content_id": 390462,
    "reference_id": 25521,
    "title": "乞求",
    "media_type": "Text",
    "index_reference": "乞求",
    "language": "zht",
    "content": "<h1>乞求、乞討、乞求</h1><h2>定義：</h2><p>「乞求（beg）」這個詞是指緊急地向某人請求某事。</p><ul><li><p>人們常常在強烈需要某物時乞求或懇求（plead），但不知道對方是否會給予他們所要求的。</p></li><li><p>根據上下文，這個詞可以翻譯為「懇求」或「緊急請求」。</p></li></ul><p>（另見：<span data-bnType=\"resourceReference\" data-resourceId=\"26108\" data-resourceType=\"UWTranslationWords\">懇求</span>）</p><h2>聖經開卷故事集中的例子：</h2><ul><li><p><strong>10:4</strong> <span>神讓埃及全地遍布青蛙，法老<strong>求</strong>摩西把青蛙變走</span>。</p></li><li><p><strong>29:8</strong> 「<span>王叫來了這僕人說：『你這惡僕！你<strong>央求</strong>我，我就免了你的債。</span>』」</p></li><li><p><strong>32:7</strong> <span>這些污鬼<strong>祈求</strong>耶穌：「請不要把我們從這地趕出來！」附近，有一群豬在山上吃食。於是，污鬼<strong>祈求</strong>耶穌：「請把我們趕到豬群里！</span>」</p></li><li><p><strong>32:10</strong> <span>那曾被鬼附的人<strong>懇求</strong>和耶穌同往</span>。</p></li><li><p><strong>35:11</strong> <span>他的父親出來<strong>懇求</strong>他進去一同慶祝，但他卻拒絕了</span>。</p></li></ul><h2></h2>",
    "associations": {
      "passage": [
        {
          "start_ref": "20020004",
          "start_ref_usfm": "PRO 20:4",
          "end_ref": "20020004",
          "end_ref_usfm": "PRO 20:4"
        },
        {
          "start_ref": "40008005",
          "start_ref_usfm": "MAT 8:5",
          "end_ref": "40008005",
          "end_ref_usfm": "MAT 8:5"
        },
        {
          "start_ref": "40008031",
          "start_ref_usfm": "MAT 8:31",
          "end_ref": "40008031",
          "end_ref_usfm": "MAT 8:31"
        },
        {
          "start_ref": "40008034",
          "start_ref_usfm": "MAT 8:34",
          "end_ref": "40008034",
          "end_ref_usfm": "MAT 8:34"
        },
        {
          "start_ref": "40009038",
          "start_ref_usfm": "MAT 9:38",
          "end_ref": "40009038",
          "end_ref_usfm": "MAT 9:38"
        },
        {
          "start_ref": "40014036",
          "start_ref_usfm": "MAT 14:36",
          "end_ref": "40014036",
          "end_ref_usfm": "MAT 14:36"
        },
        {
          "start_ref": "40018029",
          "start_ref_usfm": "MAT 18:29",
          "end_ref": "40018029",
          "end_ref_usfm": "MAT 18:29"
        },
        {
          "start_ref": "40018032",
          "start_ref_usfm": "MAT 18:32",
          "end_ref": "40018032",
          "end_ref_usfm": "MAT 18:32"
        },
        {
          "start_ref": "41001040",
          "start_ref_usfm": "MRK 1:40",
          "end_ref": "41001040",
          "end_ref_usfm": "MRK 1:40"
        },
        {
          "start_ref": "41005010",
          "start_ref_usfm": "MRK 5:10",
          "end_ref": "41005010",
          "end_ref_usfm": "MRK 5:10"
        },
        {
          "start_ref": "41005012",
          "start_ref_usfm": "MRK 5:12",
          "end_ref": "41005012",
          "end_ref_usfm": "MRK 5:12"
        },
        {
          "start_ref": "41005017",
          "start_ref_usfm": "MRK 5:17",
          "end_ref": "41005017",
          "end_ref_usfm": "MRK 5:17"
        },
        {
          "start_ref": "41005018",
          "start_ref_usfm": "MRK 5:18",
          "end_ref": "41005018",
          "end_ref_usfm": "MRK 5:18"
        },
        {
          "start_ref": "41005023",
          "start_ref_usfm": "MRK 5:23",
          "end_ref": "41005023",
          "end_ref_usfm": "MRK 5:23"
        },
        {
          "start_ref": "41006056",
          "start_ref_usfm": "MRK 6:56",
          "end_ref": "41006056",
          "end_ref_usfm": "MRK 6:56"
        },
        {
          "start_ref": "41007032",
          "start_ref_usfm": "MRK 7:32",
          "end_ref": "41007032",
          "end_ref_usfm": "MRK 7:32"
        },
        {
          "start_ref": "41008022",
          "start_ref_usfm": "MRK 8:22",
          "end_ref": "41008022",
          "end_ref_usfm": "MRK 8:22"
        },
        {
          "start_ref": "41010046",
          "start_ref_usfm": "MRK 10:46",
          "end_ref": "41010046",
          "end_ref_usfm": "MRK 10:46"
        },
        {
          "start_ref": "42005012",
          "start_ref_usfm": "LUK 5:12",
          "end_ref": "42005012",
          "end_ref_usfm": "LUK 5:12"
        },
        {
          "start_ref": "42007003",
          "start_ref_usfm": "LUK 7:3",
          "end_ref": "42007003",
          "end_ref_usfm": "LUK 7:3"
        },
        {
          "start_ref": "42007004",
          "start_ref_usfm": "LUK 7:4",
          "end_ref": "42007004",
          "end_ref_usfm": "LUK 7:4"
        },
        {
          "start_ref": "42008028",
          "start_ref_usfm": "LUK 8:28",
          "end_ref": "42008028",
          "end_ref_usfm": "LUK 8:28"
        },
        {
          "start_ref": "42008031",
          "start_ref_usfm": "LUK 8:31",
          "end_ref": "42008031",
          "end_ref_usfm": "LUK 8:31"
        },
        {
          "start_ref": "42008032",
          "start_ref_usfm": "LUK 8:32",
          "end_ref": "42008032",
          "end_ref_usfm": "LUK 8:32"
        },
        {
          "start_ref": "42008038",
          "start_ref_usfm": "LUK 8:38",
          "end_ref": "42008038",
          "end_ref_usfm": "LUK 8:38"
        },
        {
          "start_ref": "42008041",
          "start_ref_usfm": "LUK 8:41",
          "end_ref": "42008041",
          "end_ref_usfm": "LUK 8:41"
        },
        {
          "start_ref": "42009038",
          "start_ref_usfm": "LUK 9:38",
          "end_ref": "42009038",
          "end_ref_usfm": "LUK 9:38"
        },
        {
          "start_ref": "42009040",
          "start_ref_usfm": "LUK 9:40",
          "end_ref": "42009040",
          "end_ref_usfm": "LUK 9:40"
        },
        {
          "start_ref": "42016003",
          "start_ref_usfm": "LUK 16:3",
          "end_ref": "42016003",
          "end_ref_usfm": "LUK 16:3"
        },
        {
          "start_ref": "42018035",
          "start_ref_usfm": "LUK 18:35",
          "end_ref": "42018035",
          "end_ref_usfm": "LUK 18:35"
        },
        {
          "start_ref": "43009008",
          "start_ref_usfm": "JHN 9:8",
          "end_ref": "43009008",
          "end_ref_usfm": "JHN 9:8"
        },
        {
          "start_ref": "44013042",
          "start_ref_usfm": "ACT 13:42",
          "end_ref": "44013042",
          "end_ref_usfm": "ACT 13:42"
        },
        {
          "start_ref": "44016015",
          "start_ref_usfm": "ACT 16:15",
          "end_ref": "44016015",
          "end_ref_usfm": "ACT 16:15"
        },
        {
          "start_ref": "44016039",
          "start_ref_usfm": "ACT 16:39",
          "end_ref": "44016039",
          "end_ref_usfm": "ACT 16:39"
        },
        {
          "start_ref": "44021012",
          "start_ref_usfm": "ACT 21:12",
          "end_ref": "44021012",
          "end_ref_usfm": "ACT 21:12"
        },
        {
          "start_ref": "44024004",
          "start_ref_usfm": "ACT 24:4",
          "end_ref": "44024004",
          "end_ref_usfm": "ACT 24:4"
        },
        {
          "start_ref": "44025002",
          "start_ref_usfm": "ACT 25:2",
          "end_ref": "44025002",
          "end_ref_usfm": "ACT 25:2"
        },
        {
          "start_ref": "44028014",
          "start_ref_usfm": "ACT 28:14",
          "end_ref": "44028014",
          "end_ref_usfm": "ACT 28:14"
        }
      ],
      "resource": [
        {
          "reference_id": 26108,
          "content_id": 391033,
          "resource_code": "UWTranslationWords",
          "label": "懇求",
          "language": "zht"
        }
      ]
    }
  }
]