[
  {
    "content_id": 390622,
    "reference_id": 25685,
    "version": "1.0.0",
    "title": "糞土",
    "media_type": "Text",
    "index_reference": "糞土",
    "language": "zht",
    "content": "<h1>糞土、糞</h1><h2>定義：</h2><p>「糞土」一詞指的是人或動物的固體排泄物，也稱為糞便或排泄物。當用作肥料以豐富土壤時，稱為「糞」。</p><ul><li><p>這些術語可以象徵性地用來指代一些毫無價值或不重要的東西。</p></li><li><p>乾燥的動物糞土常用作燃料。</p></li><li><p>「在地上成為糞土」這個表達可以翻譯為「像無價值的糞土一樣被撒在地上」。</p></li><li><p>耶路撒冷南牆的「糞廠門」可能是用來運送垃圾和廢物出城的城門。</p></li></ul><p>（另見：<span data-bnType=\"resourceReference\" data-resourceId=\"25767\" data-resourceType=\"UWTranslationWords\">門</span>）</p><h2>參考經文：</h2><ul><li><p><a href=\"https://ref.ly/1Kgs14:10\">列王紀上14:10</a></p></li><li><p><a href=\"https://ref.ly/2Kgs6:25\">列王紀下6:25</a></p></li><li><p><a href=\"https://ref.ly/Isa25:10\">以賽亞書25:10</a></p></li><li><p><a href=\"https://ref.ly/Jer8:2\">耶利米書8:2</a></p></li></ul><h2>原文參照：</h2><ul><li><p>史特朗號：H0830，H1119，H1557，H1561，H1686，H1828，H6569，H6675，G28740</p></li></ul>",
    "associations": {
      "passage": [
        {
          "start_ref": "11014010",
          "start_ref_usfm": "1KI 14:10",
          "end_ref": "11014010",
          "end_ref_usfm": "1KI 14:10"
        },
        {
          "start_ref": "12006025",
          "start_ref_usfm": "2KI 6:25",
          "end_ref": "12006025",
          "end_ref_usfm": "2KI 6:25"
        },
        {
          "start_ref": "23025010",
          "start_ref_usfm": "ISA 25:10",
          "end_ref": "23025010",
          "end_ref_usfm": "ISA 25:10"
        },
        {
          "start_ref": "24008002",
          "start_ref_usfm": "JER 8:2",
          "end_ref": "24008002",
          "end_ref_usfm": "JER 8:2"
        }
      ],
      "resource": [
        {
          "reference_id": 25767,
          "content_id": 390701,
          "resource_code": "UWTranslationWords",
          "label": "門",
          "language": "zht"
        }
      ]
    }
  }
]