[
  {
    "content_id": 391053,
    "reference_id": 26129,
    "version": "1.0.1",
    "title": "先知",
    "media_type": "Text",
    "index_reference": "先知",
    "language": "zht",
    "review_level": "None",
    "content": "<h1>先知、預言、先見、女先知</h1><h2>定義：</h2><p>「先知」是指傳達神信息給人的人。這樣做的女性被稱為「女先知」。</p><ul><li><p>先知經常警告人要遠離罪惡，順服神。</p></li><li><p>「預言」是先知所講的訊息。「預言」的意思是講述神的訊息。</p></li><li><p>預言的信息通常是關於未來將要發生的事情。</p></li><li><p>舊約中的很多預言已經應驗。</p></li><li><p>在聖經中，由先知所寫的書籍常被稱為「先知書」。</p></li><li><p>例如，「律法和先知」這個詞語是指所有希伯來文的經文的統稱，也被稱為「舊約」。</p></li><li><p>先知的舊稱是「先見」或「看見的人」。</p></li><li><p>「先見」一詞有時候指的是假先知或從事占卜的人。</p></li></ul><h2>翻譯相關建議：</h2><ul><li><p>「先知」這個詞可以翻譯為「神的代言人」或「為神說話的人」或「傳達神信息的人」。</p></li><li><p>「先知」可以翻譯為「看見異象的人」或「從神看見未來的人」。</p></li><li><p>「女先知」這個詞可以翻譯為「神的女發言人」或「為神說話的女人」或「傳達神信息的女人」。</p></li><li><p>「預言」的翻譯方式可以包括「來自神的信息」或「先知的信息」。</p></li><li><p>「預言」這個詞可以翻譯為「宣講神的話」或「傳達神的信息」。</p><p>比喻性的表達「律法和先知」也可以翻譯為「律法書和先知書」或「所有關於神和祂子民的書籍，包括神的律法和祂的先知所宣講的內容」。 （見：提喻法）</p></li><li><p>當提到假神的先知（或先見）時，可能需要翻譯為「假先知（先見）」、「假神的先知（先見）」或「巴力的先知」。</p></li></ul><p>（另見：<span data-bnType=\"resourceReference\" data-resourceId=\"25497\" data-resourceType=\"UWTranslationWords\">巴力</span>、<span data-bnType=\"resourceReference\" data-resourceId=\"25674\" data-resourceType=\"UWTranslationWords\">占卜</span>、<span data-bnType=\"resourceReference\" data-resourceId=\"25728\" data-resourceType=\"UWTranslationWords\">假神</span>、<span data-bnType=\"resourceReference\" data-resourceId=\"25729\" data-resourceType=\"UWTranslationWords\">假先知</span>、<span data-bnType=\"resourceReference\" data-resourceId=\"25761\" data-resourceType=\"UWTranslationWords\">應驗</span>、<span data-bnType=\"resourceReference\" data-resourceId=\"25957\" data-resourceType=\"UWTranslationWords\">律法</span>、<span data-bnType=\"resourceReference\" data-resourceId=\"26338\" data-resourceType=\"UWTranslationWords\">異象</span>）</p><h2>參考經文：</h2><ul><li><p><a href=\"https://ref.ly/1Thess2:14-1Thess2:16\">帖撒羅尼迦前書2:14–16</a></p></li><li><p><a href=\"https://ref.ly/Acts3:25\">使徒行傳3:25</a></p></li><li><p><a href=\"https://ref.ly/John1:43-John1:45\">約翰福音1:43–45</a></p></li><li><p><a href=\"https://ref.ly/Mal4:4-Mal4:6\">瑪拉基書4:4–6</a></p></li><li><p><a href=\"https://ref.ly/Matt1:23\">馬太福音1:23</a></p></li><li><p><a href=\"https://ref.ly/Matt2:18\">馬太福音2:18</a></p></li><li><p><a href=\"https://ref.ly/Matt5:17\">馬太福音5:17</a></p></li><li><p><a href=\"https://ref.ly/Ps51:1\">詩篇51:1</a></p></li></ul><h2>聖經開卷故事集裡的例子：</h2><ul><li><p><strong>12:12</strong> <span>當以色列人看到埃及人都死了，他們就信了神並且知道摩西是神派來的<strong>先知</strong>。</span></p></li><li><p><strong>17:13</strong> <span>但大衛所行的事，神很不喜歡，就差<strong>先知</strong>拿單去告訴大衛他所犯的罪。</span></p></li><li><p><strong>19:1</strong> <span>在以色列人的歷史上，神一直在向他們差派<strong>先知</strong>。先知可以聽到來自神的信息並將這些信息傳給以色列民。</span></p></li><li><p><strong>19:6</strong> <span>所有的以色列人，包括四百個拜巴力的<strong>先知</strong>都來到了迦密山。</span></p></li><li><p><strong>19:17</strong> <span>大多數時候，人們不順服神。他們經常虐待<strong>先知</strong>，甚至殺掉他們。</span></p></li><li><p><strong>21:9</strong> <span>神的<strong>先知</strong>預言了許多關於彌賽亞的事情。</span></p></li><li><p><strong>43:5</strong> 「<span>這正是驗證了<strong>先知</strong>約珥所說的，『在末後的日子，我要將我的靈澆灌出來。』</span>」</p></li><li><p><strong>43:7</strong> 「<span>雖然耶穌死了，但神卻叫祂復活，這正應驗了<strong>預言</strong>，『你必不叫你的聖者腐朽在墓里。』</span>」</p></li><li><p><strong>48:12</strong> <span>摩西是宣講神話語偉大的<strong>先知</strong>，耶穌卻是最偉大的<strong>先知</strong>。祂就是神，祂所說所行的都是出自神。所以，耶穌被稱為神的道。</span></p></li></ul><h2>原文參照：</h2><ul><li><p>史特朗號：H2372，H2374，H4853，H5012，H5013，H5016，H5017，H5029，H5030，H5031，H5197，G24950，G43940，G43950，G43960，G43970，G43980，G55780</p></li></ul>",
    "associations": {
      "passage": [
        {
          "start_ref": "01020007",
          "start_ref_usfm": "GEN 20:7",
          "end_ref": "01020007",
          "end_ref_usfm": "GEN 20:7"
        },
        {
          "start_ref": "02007001",
          "start_ref_usfm": "EXO 7:1",
          "end_ref": "02007001",
          "end_ref_usfm": "EXO 7:1"
        },
        {
          "start_ref": "02015020",
          "start_ref_usfm": "EXO 15:20",
          "end_ref": "02015020",
          "end_ref_usfm": "EXO 15:20"
        },
        {
          "start_ref": "15005001",
          "start_ref_usfm": "EZR 5:1",
          "end_ref": "15005001",
          "end_ref_usfm": "EZR 5:1"
        },
        {
          "start_ref": "15005002",
          "start_ref_usfm": "EZR 5:2",
          "end_ref": "15005002",
          "end_ref_usfm": "EZR 5:2"
        },
        {
          "start_ref": "15006014",
          "start_ref_usfm": "EZR 6:14",
          "end_ref": "15006014",
          "end_ref_usfm": "EZR 6:14"
        },
        {
          "start_ref": "15009011",
          "start_ref_usfm": "EZR 9:11",
          "end_ref": "15009011",
          "end_ref_usfm": "EZR 9:11"
        },
        {
          "start_ref": "16006007",
          "start_ref_usfm": "NEH 6:7",
          "end_ref": "16006007",
          "end_ref_usfm": "NEH 6:7"
        },
        {
          "start_ref": "16006014",
          "start_ref_usfm": "NEH 6:14",
          "end_ref": "16006014",
          "end_ref_usfm": "NEH 6:14"
        },
        {
          "start_ref": "16009026",
          "start_ref_usfm": "NEH 9:26",
          "end_ref": "16009026",
          "end_ref_usfm": "NEH 9:26"
        },
        {
          "start_ref": "16009030",
          "start_ref_usfm": "NEH 9:30",
          "end_ref": "16009030",
          "end_ref_usfm": "NEH 9:30"
        },
        {
          "start_ref": "16009032",
          "start_ref_usfm": "NEH 9:32",
          "end_ref": "16009032",
          "end_ref_usfm": "NEH 9:32"
        },
        {
          "start_ref": "19051001",
          "start_ref_usfm": "PSA 51:1",
          "end_ref": "19051001",
          "end_ref_usfm": "PSA 51:1"
        },
        {
          "start_ref": "36003004",
          "start_ref_usfm": "ZEP 3:4",
          "end_ref": "36003004",
          "end_ref_usfm": "ZEP 3:4"
        },
        {
          "start_ref": "37001001",
          "start_ref_usfm": "HAG 1:1",
          "end_ref": "37001001",
          "end_ref_usfm": "HAG 1:1"
        },
        {
          "start_ref": "37001003",
          "start_ref_usfm": "HAG 1:3",
          "end_ref": "37001003",
          "end_ref_usfm": "HAG 1:3"
        },
        {
          "start_ref": "37001012",
          "start_ref_usfm": "HAG 1:12",
          "end_ref": "37001012",
          "end_ref_usfm": "HAG 1:12"
        },
        {
          "start_ref": "37002001",
          "start_ref_usfm": "HAG 2:1",
          "end_ref": "37002001",
          "end_ref_usfm": "HAG 2:1"
        },
        {
          "start_ref": "37002010",
          "start_ref_usfm": "HAG 2:10",
          "end_ref": "37002010",
          "end_ref_usfm": "HAG 2:10"
        },
        {
          "start_ref": "40001022",
          "start_ref_usfm": "MAT 1:22",
          "end_ref": "40001022",
          "end_ref_usfm": "MAT 1:22"
        },
        {
          "start_ref": "40001023",
          "start_ref_usfm": "MAT 1:23",
          "end_ref": "40001023",
          "end_ref_usfm": "MAT 1:23"
        },
        {
          "start_ref": "40002005",
          "start_ref_usfm": "MAT 2:5",
          "end_ref": "40002005",
          "end_ref_usfm": "MAT 2:5"
        },
        {
          "start_ref": "40002015",
          "start_ref_usfm": "MAT 2:15",
          "end_ref": "40002015",
          "end_ref_usfm": "MAT 2:15"
        },
        {
          "start_ref": "40002017",
          "start_ref_usfm": "MAT 2:17",
          "end_ref": "40002017",
          "end_ref_usfm": "MAT 2:17"
        },
        {
          "start_ref": "40002018",
          "start_ref_usfm": "MAT 2:18",
          "end_ref": "40002018",
          "end_ref_usfm": "MAT 2:18"
        },
        {
          "start_ref": "40002023",
          "start_ref_usfm": "MAT 2:23",
          "end_ref": "40002023",
          "end_ref_usfm": "MAT 2:23"
        },
        {
          "start_ref": "40003003",
          "start_ref_usfm": "MAT 3:3",
          "end_ref": "40003003",
          "end_ref_usfm": "MAT 3:3"
        },
        {
          "start_ref": "40004014",
          "start_ref_usfm": "MAT 4:14",
          "end_ref": "40004014",
          "end_ref_usfm": "MAT 4:14"
        },
        {
          "start_ref": "40005012",
          "start_ref_usfm": "MAT 5:12",
          "end_ref": "40005012",
          "end_ref_usfm": "MAT 5:12"
        },
        {
          "start_ref": "40005017",
          "start_ref_usfm": "MAT 5:17",
          "end_ref": "40005017",
          "end_ref_usfm": "MAT 5:17"
        },
        {
          "start_ref": "40007012",
          "start_ref_usfm": "MAT 7:12",
          "end_ref": "40007012",
          "end_ref_usfm": "MAT 7:12"
        },
        {
          "start_ref": "40007022",
          "start_ref_usfm": "MAT 7:22",
          "end_ref": "40007022",
          "end_ref_usfm": "MAT 7:22"
        },
        {
          "start_ref": "40008017",
          "start_ref_usfm": "MAT 8:17",
          "end_ref": "40008017",
          "end_ref_usfm": "MAT 8:17"
        },
        {
          "start_ref": "40010041",
          "start_ref_usfm": "MAT 10:41",
          "end_ref": "40010041",
          "end_ref_usfm": "MAT 10:41"
        },
        {
          "start_ref": "40011009",
          "start_ref_usfm": "MAT 11:9",
          "end_ref": "40011009",
          "end_ref_usfm": "MAT 11:9"
        },
        {
          "start_ref": "40011013",
          "start_ref_usfm": "MAT 11:13",
          "end_ref": "40011013",
          "end_ref_usfm": "MAT 11:13"
        },
        {
          "start_ref": "40012017",
          "start_ref_usfm": "MAT 12:17",
          "end_ref": "40012017",
          "end_ref_usfm": "MAT 12:17"
        },
        {
          "start_ref": "40012039",
          "start_ref_usfm": "MAT 12:39",
          "end_ref": "40012039",
          "end_ref_usfm": "MAT 12:39"
        },
        {
          "start_ref": "40013014",
          "start_ref_usfm": "MAT 13:14",
          "end_ref": "40013014",
          "end_ref_usfm": "MAT 13:14"
        },
        {
          "start_ref": "40013017",
          "start_ref_usfm": "MAT 13:17",
          "end_ref": "40013017",
          "end_ref_usfm": "MAT 13:17"
        },
        {
          "start_ref": "40013035",
          "start_ref_usfm": "MAT 13:35",
          "end_ref": "40013035",
          "end_ref_usfm": "MAT 13:35"
        },
        {
          "start_ref": "40013057",
          "start_ref_usfm": "MAT 13:57",
          "end_ref": "40013057",
          "end_ref_usfm": "MAT 13:57"
        },
        {
          "start_ref": "40014005",
          "start_ref_usfm": "MAT 14:5",
          "end_ref": "40014005",
          "end_ref_usfm": "MAT 14:5"
        },
        {
          "start_ref": "40015007",
          "start_ref_usfm": "MAT 15:7",
          "end_ref": "40015007",
          "end_ref_usfm": "MAT 15:7"
        },
        {
          "start_ref": "40016014",
          "start_ref_usfm": "MAT 16:14",
          "end_ref": "40016014",
          "end_ref_usfm": "MAT 16:14"
        },
        {
          "start_ref": "40021004",
          "start_ref_usfm": "MAT 21:4",
          "end_ref": "40021004",
          "end_ref_usfm": "MAT 21:4"
        },
        {
          "start_ref": "40021011",
          "start_ref_usfm": "MAT 21:11",
          "end_ref": "40021011",
          "end_ref_usfm": "MAT 21:11"
        },
        {
          "start_ref": "40021026",
          "start_ref_usfm": "MAT 21:26",
          "end_ref": "40021026",
          "end_ref_usfm": "MAT 21:26"
        },
        {
          "start_ref": "40021046",
          "start_ref_usfm": "MAT 21:46",
          "end_ref": "40021046",
          "end_ref_usfm": "MAT 21:46"
        },
        {
          "start_ref": "40022040",
          "start_ref_usfm": "MAT 22:40",
          "end_ref": "40022040",
          "end_ref_usfm": "MAT 22:40"
        },
        {
          "start_ref": "40023029",
          "start_ref_usfm": "MAT 23:29",
          "end_ref": "40023029",
          "end_ref_usfm": "MAT 23:29"
        },
        {
          "start_ref": "40023030",
          "start_ref_usfm": "MAT 23:30",
          "end_ref": "40023030",
          "end_ref_usfm": "MAT 23:30"
        },
        {
          "start_ref": "40023031",
          "start_ref_usfm": "MAT 23:31",
          "end_ref": "40023031",
          "end_ref_usfm": "MAT 23:31"
        },
        {
          "start_ref": "40023034",
          "start_ref_usfm": "MAT 23:34",
          "end_ref": "40023034",
          "end_ref_usfm": "MAT 23:34"
        },
        {
          "start_ref": "40023037",
          "start_ref_usfm": "MAT 23:37",
          "end_ref": "40023037",
          "end_ref_usfm": "MAT 23:37"
        },
        {
          "start_ref": "40024015",
          "start_ref_usfm": "MAT 24:15",
          "end_ref": "40024015",
          "end_ref_usfm": "MAT 24:15"
        },
        {
          "start_ref": "40026056",
          "start_ref_usfm": "MAT 26:56",
          "end_ref": "40026056",
          "end_ref_usfm": "MAT 26:56"
        },
        {
          "start_ref": "40026068",
          "start_ref_usfm": "MAT 26:68",
          "end_ref": "40026068",
          "end_ref_usfm": "MAT 26:68"
        },
        {
          "start_ref": "40027009",
          "start_ref_usfm": "MAT 27:9",
          "end_ref": "40027009",
          "end_ref_usfm": "MAT 27:9"
        },
        {
          "start_ref": "41001002",
          "start_ref_usfm": "MRK 1:2",
          "end_ref": "41001002",
          "end_ref_usfm": "MRK 1:2"
        },
        {
          "start_ref": "41006004",
          "start_ref_usfm": "MRK 6:4",
          "end_ref": "41006004",
          "end_ref_usfm": "MRK 6:4"
        },
        {
          "start_ref": "41006015",
          "start_ref_usfm": "MRK 6:15",
          "end_ref": "41006015",
          "end_ref_usfm": "MRK 6:15"
        },
        {
          "start_ref": "41007006",
          "start_ref_usfm": "MRK 7:6",
          "end_ref": "41007006",
          "end_ref_usfm": "MRK 7:6"
        },
        {
          "start_ref": "41008028",
          "start_ref_usfm": "MRK 8:28",
          "end_ref": "41008028",
          "end_ref_usfm": "MRK 8:28"
        },
        {
          "start_ref": "41011032",
          "start_ref_usfm": "MRK 11:32",
          "end_ref": "41011032",
          "end_ref_usfm": "MRK 11:32"
        },
        {
          "start_ref": "41014065",
          "start_ref_usfm": "MRK 14:65",
          "end_ref": "41014065",
          "end_ref_usfm": "MRK 14:65"
        },
        {
          "start_ref": "42001067",
          "start_ref_usfm": "LUK 1:67",
          "end_ref": "42001067",
          "end_ref_usfm": "LUK 1:67"
        },
        {
          "start_ref": "42001070",
          "start_ref_usfm": "LUK 1:70",
          "end_ref": "42001070",
          "end_ref_usfm": "LUK 1:70"
        },
        {
          "start_ref": "42001076",
          "start_ref_usfm": "LUK 1:76",
          "end_ref": "42001076",
          "end_ref_usfm": "LUK 1:76"
        },
        {
          "start_ref": "42002036",
          "start_ref_usfm": "LUK 2:36",
          "end_ref": "42002036",
          "end_ref_usfm": "LUK 2:36"
        },
        {
          "start_ref": "42003004",
          "start_ref_usfm": "LUK 3:4",
          "end_ref": "42003004",
          "end_ref_usfm": "LUK 3:4"
        },
        {
          "start_ref": "42004017",
          "start_ref_usfm": "LUK 4:17",
          "end_ref": "42004017",
          "end_ref_usfm": "LUK 4:17"
        },
        {
          "start_ref": "42004024",
          "start_ref_usfm": "LUK 4:24",
          "end_ref": "42004024",
          "end_ref_usfm": "LUK 4:24"
        },
        {
          "start_ref": "42004027",
          "start_ref_usfm": "LUK 4:27",
          "end_ref": "42004027",
          "end_ref_usfm": "LUK 4:27"
        },
        {
          "start_ref": "42006023",
          "start_ref_usfm": "LUK 6:23",
          "end_ref": "42006023",
          "end_ref_usfm": "LUK 6:23"
        },
        {
          "start_ref": "42007016",
          "start_ref_usfm": "LUK 7:16",
          "end_ref": "42007016",
          "end_ref_usfm": "LUK 7:16"
        },
        {
          "start_ref": "42007026",
          "start_ref_usfm": "LUK 7:26",
          "end_ref": "42007026",
          "end_ref_usfm": "LUK 7:26"
        },
        {
          "start_ref": "42007039",
          "start_ref_usfm": "LUK 7:39",
          "end_ref": "42007039",
          "end_ref_usfm": "LUK 7:39"
        },
        {
          "start_ref": "42009008",
          "start_ref_usfm": "LUK 9:8",
          "end_ref": "42009008",
          "end_ref_usfm": "LUK 9:8"
        },
        {
          "start_ref": "42009019",
          "start_ref_usfm": "LUK 9:19",
          "end_ref": "42009019",
          "end_ref_usfm": "LUK 9:19"
        },
        {
          "start_ref": "42010024",
          "start_ref_usfm": "LUK 10:24",
          "end_ref": "42010024",
          "end_ref_usfm": "LUK 10:24"
        },
        {
          "start_ref": "42011047",
          "start_ref_usfm": "LUK 11:47",
          "end_ref": "42011047",
          "end_ref_usfm": "LUK 11:47"
        },
        {
          "start_ref": "42011049",
          "start_ref_usfm": "LUK 11:49",
          "end_ref": "42011049",
          "end_ref_usfm": "LUK 11:49"
        },
        {
          "start_ref": "42011050",
          "start_ref_usfm": "LUK 11:50",
          "end_ref": "42011050",
          "end_ref_usfm": "LUK 11:50"
        },
        {
          "start_ref": "42013028",
          "start_ref_usfm": "LUK 13:28",
          "end_ref": "42013028",
          "end_ref_usfm": "LUK 13:28"
        },
        {
          "start_ref": "42013033",
          "start_ref_usfm": "LUK 13:33",
          "end_ref": "42013033",
          "end_ref_usfm": "LUK 13:33"
        },
        {
          "start_ref": "42013034",
          "start_ref_usfm": "LUK 13:34",
          "end_ref": "42013034",
          "end_ref_usfm": "LUK 13:34"
        },
        {
          "start_ref": "42016016",
          "start_ref_usfm": "LUK 16:16",
          "end_ref": "42016016",
          "end_ref_usfm": "LUK 16:16"
        },
        {
          "start_ref": "42016029",
          "start_ref_usfm": "LUK 16:29",
          "end_ref": "42016029",
          "end_ref_usfm": "LUK 16:29"
        },
        {
          "start_ref": "42016031",
          "start_ref_usfm": "LUK 16:31",
          "end_ref": "42016031",
          "end_ref_usfm": "LUK 16:31"
        },
        {
          "start_ref": "42018031",
          "start_ref_usfm": "LUK 18:31",
          "end_ref": "42018031",
          "end_ref_usfm": "LUK 18:31"
        },
        {
          "start_ref": "42020006",
          "start_ref_usfm": "LUK 20:6",
          "end_ref": "42020006",
          "end_ref_usfm": "LUK 20:6"
        },
        {
          "start_ref": "42022064",
          "start_ref_usfm": "LUK 22:64",
          "end_ref": "42022064",
          "end_ref_usfm": "LUK 22:64"
        },
        {
          "start_ref": "42024019",
          "start_ref_usfm": "LUK 24:19",
          "end_ref": "42024019",
          "end_ref_usfm": "LUK 24:19"
        },
        {
          "start_ref": "42024025",
          "start_ref_usfm": "LUK 24:25",
          "end_ref": "42024025",
          "end_ref_usfm": "LUK 24:25"
        },
        {
          "start_ref": "42024027",
          "start_ref_usfm": "LUK 24:27",
          "end_ref": "42024027",
          "end_ref_usfm": "LUK 24:27"
        },
        {
          "start_ref": "42024044",
          "start_ref_usfm": "LUK 24:44",
          "end_ref": "42024044",
          "end_ref_usfm": "LUK 24:44"
        },
        {
          "start_ref": "43001021",
          "start_ref_usfm": "JHN 1:21",
          "end_ref": "43001021",
          "end_ref_usfm": "JHN 1:21"
        },
        {
          "start_ref": "43001023",
          "start_ref_usfm": "JHN 1:23",
          "end_ref": "43001023",
          "end_ref_usfm": "JHN 1:23"
        },
        {
          "start_ref": "43001025",
          "start_ref_usfm": "JHN 1:25",
          "end_ref": "43001025",
          "end_ref_usfm": "JHN 1:25"
        },
        {
          "start_ref": "43001045",
          "start_ref_usfm": "JHN 1:45",
          "end_ref": "43001045",
          "end_ref_usfm": "JHN 1:45"
        },
        {
          "start_ref": "43004019",
          "start_ref_usfm": "JHN 4:19",
          "end_ref": "43004019",
          "end_ref_usfm": "JHN 4:19"
        },
        {
          "start_ref": "43004044",
          "start_ref_usfm": "JHN 4:44",
          "end_ref": "43004044",
          "end_ref_usfm": "JHN 4:44"
        },
        {
          "start_ref": "43006014",
          "start_ref_usfm": "JHN 6:14",
          "end_ref": "43006014",
          "end_ref_usfm": "JHN 6:14"
        },
        {
          "start_ref": "43006045",
          "start_ref_usfm": "JHN 6:45",
          "end_ref": "43006045",
          "end_ref_usfm": "JHN 6:45"
        },
        {
          "start_ref": "43007040",
          "start_ref_usfm": "JHN 7:40",
          "end_ref": "43007040",
          "end_ref_usfm": "JHN 7:40"
        },
        {
          "start_ref": "43007052",
          "start_ref_usfm": "JHN 7:52",
          "end_ref": "43007052",
          "end_ref_usfm": "JHN 7:52"
        },
        {
          "start_ref": "43008052",
          "start_ref_usfm": "JHN 8:52",
          "end_ref": "43008052",
          "end_ref_usfm": "JHN 8:52"
        },
        {
          "start_ref": "43008053",
          "start_ref_usfm": "JHN 8:53",
          "end_ref": "43008053",
          "end_ref_usfm": "JHN 8:53"
        },
        {
          "start_ref": "43009017",
          "start_ref_usfm": "JHN 9:17",
          "end_ref": "43009017",
          "end_ref_usfm": "JHN 9:17"
        },
        {
          "start_ref": "43011051",
          "start_ref_usfm": "JHN 11:51",
          "end_ref": "43011051",
          "end_ref_usfm": "JHN 11:51"
        },
        {
          "start_ref": "43012038",
          "start_ref_usfm": "JHN 12:38",
          "end_ref": "43012038",
          "end_ref_usfm": "JHN 12:38"
        },
        {
          "start_ref": "44002016",
          "start_ref_usfm": "ACT 2:16",
          "end_ref": "44002016",
          "end_ref_usfm": "ACT 2:16"
        },
        {
          "start_ref": "44002017",
          "start_ref_usfm": "ACT 2:17",
          "end_ref": "44002017",
          "end_ref_usfm": "ACT 2:17"
        },
        {
          "start_ref": "44002018",
          "start_ref_usfm": "ACT 2:18",
          "end_ref": "44002018",
          "end_ref_usfm": "ACT 2:18"
        },
        {
          "start_ref": "44002030",
          "start_ref_usfm": "ACT 2:30",
          "end_ref": "44002030",
          "end_ref_usfm": "ACT 2:30"
        },
        {
          "start_ref": "44003018",
          "start_ref_usfm": "ACT 3:18",
          "end_ref": "44003018",
          "end_ref_usfm": "ACT 3:18"
        },
        {
          "start_ref": "44003021",
          "start_ref_usfm": "ACT 3:21",
          "end_ref": "44003021",
          "end_ref_usfm": "ACT 3:21"
        },
        {
          "start_ref": "44003022",
          "start_ref_usfm": "ACT 3:22",
          "end_ref": "44003022",
          "end_ref_usfm": "ACT 3:22"
        },
        {
          "start_ref": "44003023",
          "start_ref_usfm": "ACT 3:23",
          "end_ref": "44003023",
          "end_ref_usfm": "ACT 3:23"
        },
        {
          "start_ref": "44003024",
          "start_ref_usfm": "ACT 3:24",
          "end_ref": "44003024",
          "end_ref_usfm": "ACT 3:24"
        },
        {
          "start_ref": "44003025",
          "start_ref_usfm": "ACT 3:25",
          "end_ref": "44003025",
          "end_ref_usfm": "ACT 3:25"
        },
        {
          "start_ref": "44007037",
          "start_ref_usfm": "ACT 7:37",
          "end_ref": "44007037",
          "end_ref_usfm": "ACT 7:37"
        },
        {
          "start_ref": "44007042",
          "start_ref_usfm": "ACT 7:42",
          "end_ref": "44007042",
          "end_ref_usfm": "ACT 7:42"
        },
        {
          "start_ref": "44007048",
          "start_ref_usfm": "ACT 7:48",
          "end_ref": "44007048",
          "end_ref_usfm": "ACT 7:48"
        },
        {
          "start_ref": "44007052",
          "start_ref_usfm": "ACT 7:52",
          "end_ref": "44007052",
          "end_ref_usfm": "ACT 7:52"
        },
        {
          "start_ref": "44008028",
          "start_ref_usfm": "ACT 8:28",
          "end_ref": "44008028",
          "end_ref_usfm": "ACT 8:28"
        },
        {
          "start_ref": "44008030",
          "start_ref_usfm": "ACT 8:30",
          "end_ref": "44008030",
          "end_ref_usfm": "ACT 8:30"
        },
        {
          "start_ref": "44008034",
          "start_ref_usfm": "ACT 8:34",
          "end_ref": "44008034",
          "end_ref_usfm": "ACT 8:34"
        },
        {
          "start_ref": "44010043",
          "start_ref_usfm": "ACT 10:43",
          "end_ref": "44010043",
          "end_ref_usfm": "ACT 10:43"
        },
        {
          "start_ref": "44011027",
          "start_ref_usfm": "ACT 11:27",
          "end_ref": "44011027",
          "end_ref_usfm": "ACT 11:27"
        },
        {
          "start_ref": "44013001",
          "start_ref_usfm": "ACT 13:1",
          "end_ref": "44013001",
          "end_ref_usfm": "ACT 13:1"
        },
        {
          "start_ref": "44013015",
          "start_ref_usfm": "ACT 13:15",
          "end_ref": "44013015",
          "end_ref_usfm": "ACT 13:15"
        },
        {
          "start_ref": "44013020",
          "start_ref_usfm": "ACT 13:20",
          "end_ref": "44013020",
          "end_ref_usfm": "ACT 13:20"
        },
        {
          "start_ref": "44013027",
          "start_ref_usfm": "ACT 13:27",
          "end_ref": "44013027",
          "end_ref_usfm": "ACT 13:27"
        },
        {
          "start_ref": "44013040",
          "start_ref_usfm": "ACT 13:40",
          "end_ref": "44013040",
          "end_ref_usfm": "ACT 13:40"
        },
        {
          "start_ref": "44015015",
          "start_ref_usfm": "ACT 15:15",
          "end_ref": "44015015",
          "end_ref_usfm": "ACT 15:15"
        },
        {
          "start_ref": "44015032",
          "start_ref_usfm": "ACT 15:32",
          "end_ref": "44015032",
          "end_ref_usfm": "ACT 15:32"
        },
        {
          "start_ref": "44019006",
          "start_ref_usfm": "ACT 19:6",
          "end_ref": "44019006",
          "end_ref_usfm": "ACT 19:6"
        },
        {
          "start_ref": "44021009",
          "start_ref_usfm": "ACT 21:9",
          "end_ref": "44021009",
          "end_ref_usfm": "ACT 21:9"
        },
        {
          "start_ref": "44021010",
          "start_ref_usfm": "ACT 21:10",
          "end_ref": "44021010",
          "end_ref_usfm": "ACT 21:10"
        },
        {
          "start_ref": "44024014",
          "start_ref_usfm": "ACT 24:14",
          "end_ref": "44024014",
          "end_ref_usfm": "ACT 24:14"
        },
        {
          "start_ref": "44026022",
          "start_ref_usfm": "ACT 26:22",
          "end_ref": "44026022",
          "end_ref_usfm": "ACT 26:22"
        },
        {
          "start_ref": "44026027",
          "start_ref_usfm": "ACT 26:27",
          "end_ref": "44026027",
          "end_ref_usfm": "ACT 26:27"
        },
        {
          "start_ref": "44028023",
          "start_ref_usfm": "ACT 28:23",
          "end_ref": "44028023",
          "end_ref_usfm": "ACT 28:23"
        },
        {
          "start_ref": "44028025",
          "start_ref_usfm": "ACT 28:25",
          "end_ref": "44028025",
          "end_ref_usfm": "ACT 28:25"
        },
        {
          "start_ref": "45001002",
          "start_ref_usfm": "ROM 1:2",
          "end_ref": "45001002",
          "end_ref_usfm": "ROM 1:2"
        },
        {
          "start_ref": "45003021",
          "start_ref_usfm": "ROM 3:21",
          "end_ref": "45003021",
          "end_ref_usfm": "ROM 3:21"
        },
        {
          "start_ref": "45011003",
          "start_ref_usfm": "ROM 11:3",
          "end_ref": "45011003",
          "end_ref_usfm": "ROM 11:3"
        },
        {
          "start_ref": "45012006",
          "start_ref_usfm": "ROM 12:6",
          "end_ref": "45012006",
          "end_ref_usfm": "ROM 12:6"
        },
        {
          "start_ref": "45016026",
          "start_ref_usfm": "ROM 16:26",
          "end_ref": "45016026",
          "end_ref_usfm": "ROM 16:26"
        },
        {
          "start_ref": "46011004",
          "start_ref_usfm": "1CO 11:4",
          "end_ref": "46011004",
          "end_ref_usfm": "1CO 11:4"
        },
        {
          "start_ref": "46011005",
          "start_ref_usfm": "1CO 11:5",
          "end_ref": "46011005",
          "end_ref_usfm": "1CO 11:5"
        },
        {
          "start_ref": "46012010",
          "start_ref_usfm": "1CO 12:10",
          "end_ref": "46012010",
          "end_ref_usfm": "1CO 12:10"
        },
        {
          "start_ref": "46012028",
          "start_ref_usfm": "1CO 12:28",
          "end_ref": "46012028",
          "end_ref_usfm": "1CO 12:28"
        },
        {
          "start_ref": "46012029",
          "start_ref_usfm": "1CO 12:29",
          "end_ref": "46012029",
          "end_ref_usfm": "1CO 12:29"
        },
        {
          "start_ref": "46013002",
          "start_ref_usfm": "1CO 13:2",
          "end_ref": "46013002",
          "end_ref_usfm": "1CO 13:2"
        },
        {
          "start_ref": "46013008",
          "start_ref_usfm": "1CO 13:8",
          "end_ref": "46013008",
          "end_ref_usfm": "1CO 13:8"
        },
        {
          "start_ref": "46013009",
          "start_ref_usfm": "1CO 13:9",
          "end_ref": "46013009",
          "end_ref_usfm": "1CO 13:9"
        },
        {
          "start_ref": "46014001",
          "start_ref_usfm": "1CO 14:1",
          "end_ref": "46014001",
          "end_ref_usfm": "1CO 14:1"
        },
        {
          "start_ref": "46014003",
          "start_ref_usfm": "1CO 14:3",
          "end_ref": "46014003",
          "end_ref_usfm": "1CO 14:3"
        },
        {
          "start_ref": "46014004",
          "start_ref_usfm": "1CO 14:4",
          "end_ref": "46014004",
          "end_ref_usfm": "1CO 14:4"
        },
        {
          "start_ref": "46014005",
          "start_ref_usfm": "1CO 14:5",
          "end_ref": "46014005",
          "end_ref_usfm": "1CO 14:5"
        },
        {
          "start_ref": "46014006",
          "start_ref_usfm": "1CO 14:6",
          "end_ref": "46014006",
          "end_ref_usfm": "1CO 14:6"
        },
        {
          "start_ref": "46014022",
          "start_ref_usfm": "1CO 14:22",
          "end_ref": "46014022",
          "end_ref_usfm": "1CO 14:22"
        },
        {
          "start_ref": "46014024",
          "start_ref_usfm": "1CO 14:24",
          "end_ref": "46014024",
          "end_ref_usfm": "1CO 14:24"
        },
        {
          "start_ref": "46014029",
          "start_ref_usfm": "1CO 14:29",
          "end_ref": "46014029",
          "end_ref_usfm": "1CO 14:29"
        },
        {
          "start_ref": "46014031",
          "start_ref_usfm": "1CO 14:31",
          "end_ref": "46014031",
          "end_ref_usfm": "1CO 14:31"
        },
        {
          "start_ref": "46014032",
          "start_ref_usfm": "1CO 14:32",
          "end_ref": "46014032",
          "end_ref_usfm": "1CO 14:32"
        },
        {
          "start_ref": "46014037",
          "start_ref_usfm": "1CO 14:37",
          "end_ref": "46014037",
          "end_ref_usfm": "1CO 14:37"
        },
        {
          "start_ref": "46014039",
          "start_ref_usfm": "1CO 14:39",
          "end_ref": "46014039",
          "end_ref_usfm": "1CO 14:39"
        },
        {
          "start_ref": "49002020",
          "start_ref_usfm": "EPH 2:20",
          "end_ref": "49002020",
          "end_ref_usfm": "EPH 2:20"
        },
        {
          "start_ref": "49003005",
          "start_ref_usfm": "EPH 3:5",
          "end_ref": "49003005",
          "end_ref_usfm": "EPH 3:5"
        },
        {
          "start_ref": "49004011",
          "start_ref_usfm": "EPH 4:11",
          "end_ref": "49004011",
          "end_ref_usfm": "EPH 4:11"
        },
        {
          "start_ref": "52002015",
          "start_ref_usfm": "1TH 2:15",
          "end_ref": "52002015",
          "end_ref_usfm": "1TH 2:15"
        },
        {
          "start_ref": "52005020",
          "start_ref_usfm": "1TH 5:20",
          "end_ref": "52005020",
          "end_ref_usfm": "1TH 5:20"
        },
        {
          "start_ref": "54001018",
          "start_ref_usfm": "1TI 1:18",
          "end_ref": "54001018",
          "end_ref_usfm": "1TI 1:18"
        },
        {
          "start_ref": "54004014",
          "start_ref_usfm": "1TI 4:14",
          "end_ref": "54004014",
          "end_ref_usfm": "1TI 4:14"
        },
        {
          "start_ref": "56001012",
          "start_ref_usfm": "TIT 1:12",
          "end_ref": "56001012",
          "end_ref_usfm": "TIT 1:12"
        },
        {
          "start_ref": "58001001",
          "start_ref_usfm": "HEB 1:1",
          "end_ref": "58001001",
          "end_ref_usfm": "HEB 1:1"
        },
        {
          "start_ref": "58011032",
          "start_ref_usfm": "HEB 11:32",
          "end_ref": "58011032",
          "end_ref_usfm": "HEB 11:32"
        },
        {
          "start_ref": "59005010",
          "start_ref_usfm": "JAS 5:10",
          "end_ref": "59005010",
          "end_ref_usfm": "JAS 5:10"
        },
        {
          "start_ref": "60001010",
          "start_ref_usfm": "1PE 1:10",
          "end_ref": "60001010",
          "end_ref_usfm": "1PE 1:10"
        },
        {
          "start_ref": "61001019",
          "start_ref_usfm": "2PE 1:19",
          "end_ref": "61001019",
          "end_ref_usfm": "2PE 1:19"
        },
        {
          "start_ref": "61001020",
          "start_ref_usfm": "2PE 1:20",
          "end_ref": "61001020",
          "end_ref_usfm": "2PE 1:20"
        },
        {
          "start_ref": "61001021",
          "start_ref_usfm": "2PE 1:21",
          "end_ref": "61001021",
          "end_ref_usfm": "2PE 1:21"
        },
        {
          "start_ref": "61002016",
          "start_ref_usfm": "2PE 2:16",
          "end_ref": "61002016",
          "end_ref_usfm": "2PE 2:16"
        },
        {
          "start_ref": "61003002",
          "start_ref_usfm": "2PE 3:2",
          "end_ref": "61003002",
          "end_ref_usfm": "2PE 3:2"
        },
        {
          "start_ref": "65001014",
          "start_ref_usfm": "JUD 1:14",
          "end_ref": "65001014",
          "end_ref_usfm": "JUD 1:14"
        },
        {
          "start_ref": "66001003",
          "start_ref_usfm": "REV 1:3",
          "end_ref": "66001003",
          "end_ref_usfm": "REV 1:3"
        },
        {
          "start_ref": "66002020",
          "start_ref_usfm": "REV 2:20",
          "end_ref": "66002020",
          "end_ref_usfm": "REV 2:20"
        },
        {
          "start_ref": "66010007",
          "start_ref_usfm": "REV 10:7",
          "end_ref": "66010007",
          "end_ref_usfm": "REV 10:7"
        },
        {
          "start_ref": "66010011",
          "start_ref_usfm": "REV 10:11",
          "end_ref": "66010011",
          "end_ref_usfm": "REV 10:11"
        },
        {
          "start_ref": "66011003",
          "start_ref_usfm": "REV 11:3",
          "end_ref": "66011003",
          "end_ref_usfm": "REV 11:3"
        },
        {
          "start_ref": "66011006",
          "start_ref_usfm": "REV 11:6",
          "end_ref": "66011006",
          "end_ref_usfm": "REV 11:6"
        },
        {
          "start_ref": "66011010",
          "start_ref_usfm": "REV 11:10",
          "end_ref": "66011010",
          "end_ref_usfm": "REV 11:10"
        },
        {
          "start_ref": "66011018",
          "start_ref_usfm": "REV 11:18",
          "end_ref": "66011018",
          "end_ref_usfm": "REV 11:18"
        },
        {
          "start_ref": "66016006",
          "start_ref_usfm": "REV 16:6",
          "end_ref": "66016006",
          "end_ref_usfm": "REV 16:6"
        },
        {
          "start_ref": "66018020",
          "start_ref_usfm": "REV 18:20",
          "end_ref": "66018020",
          "end_ref_usfm": "REV 18:20"
        },
        {
          "start_ref": "66018024",
          "start_ref_usfm": "REV 18:24",
          "end_ref": "66018024",
          "end_ref_usfm": "REV 18:24"
        },
        {
          "start_ref": "66019010",
          "start_ref_usfm": "REV 19:10",
          "end_ref": "66019010",
          "end_ref_usfm": "REV 19:10"
        },
        {
          "start_ref": "66022006",
          "start_ref_usfm": "REV 22:6",
          "end_ref": "66022006",
          "end_ref_usfm": "REV 22:6"
        },
        {
          "start_ref": "66022007",
          "start_ref_usfm": "REV 22:7",
          "end_ref": "66022007",
          "end_ref_usfm": "REV 22:7"
        },
        {
          "start_ref": "66022009",
          "start_ref_usfm": "REV 22:9",
          "end_ref": "66022009",
          "end_ref_usfm": "REV 22:9"
        },
        {
          "start_ref": "66022010",
          "start_ref_usfm": "REV 22:10",
          "end_ref": "66022010",
          "end_ref_usfm": "REV 22:10"
        },
        {
          "start_ref": "66022018",
          "start_ref_usfm": "REV 22:18",
          "end_ref": "66022018",
          "end_ref_usfm": "REV 22:18"
        },
        {
          "start_ref": "66022019",
          "start_ref_usfm": "REV 22:19",
          "end_ref": "66022019",
          "end_ref_usfm": "REV 22:19"
        },
        {
          "start_ref": "39004004",
          "start_ref_usfm": "MAL 4:4",
          "end_ref": "39004006",
          "end_ref_usfm": "MAL 4:6"
        },
        {
          "start_ref": "43001043",
          "start_ref_usfm": "JHN 1:43",
          "end_ref": "43001045",
          "end_ref_usfm": "JHN 1:45"
        },
        {
          "start_ref": "52002014",
          "start_ref_usfm": "1TH 2:14",
          "end_ref": "52002016",
          "end_ref_usfm": "1TH 2:16"
        }
      ],
      "resource": [
        {
          "reference_id": 25497,
          "content_id": 390438,
          "resource_code": "UWTranslationWords",
          "label": "巴力",
          "language": "zht"
        },
        {
          "reference_id": 25674,
          "content_id": 390611,
          "resource_code": "UWTranslationWords",
          "label": "占卜",
          "language": "zht"
        },
        {
          "reference_id": 25728,
          "content_id": 390662,
          "resource_code": "UWTranslationWords",
          "label": "假神",
          "language": "zht"
        },
        {
          "reference_id": 25729,
          "content_id": 390663,
          "resource_code": "UWTranslationWords",
          "label": "假先知",
          "language": "zht"
        },
        {
          "reference_id": 25761,
          "content_id": 390695,
          "resource_code": "UWTranslationWords",
          "label": "應驗",
          "language": "zht"
        },
        {
          "reference_id": 25957,
          "content_id": 390885,
          "resource_code": "UWTranslationWords",
          "label": "法律",
          "language": "zht"
        },
        {
          "reference_id": 25959,
          "content_id": 390887,
          "resource_code": "Unknown",
          "label": "摩西律法",
          "language": "zht"
        },
        {
          "reference_id": 26338,
          "content_id": 391258,
          "resource_code": "UWTranslationWords",
          "label": "異象",
          "language": "zht"
        }
      ]
    }
  },
  {
    "content_id": 391110,
    "reference_id": 26188,
    "version": "1.0.1",
    "title": "獻祭",
    "media_type": "Text",
    "index_reference": "獻祭",
    "language": "zht",
    "review_level": "None",
    "content": "<h1>獻祭、犧牲、祭物</h1><h2>定義：</h2><p>在聖經中，「獻祭」和「祭物」指的是作為敬拜神的行為而獻給神的特別禮物。人們也向假神獻祭。</p><h3>獻祭</h3><ul><li><p>獻給神的祭物通常涉及宰殺動物。</p></li><li><p>唯有耶穌，神完美無罪的兒子所獻的祭，才能完全潔淨人的罪；動物的祭永遠無法做到這一點。</p></li></ul><h3>祭物</h3><ul><li><p>「祭物」一詞通常指任何供奉或獻上的東西。「犧牲」一詞指的是付上巨大的代價所給予或做出的事情。</p></li><li><p>獻給神的祭物是祂命令以色列人獻上的特定物品，以表達對祂的忠心和順服。</p></li><li><p>不同祭物的名稱，如「燔祭」和「平安祭」，表明了所獻祭物的種類。</p></li></ul><h2>翻譯相關建議</h2><ul><li><p>「祭物」這個詞也可以翻譯為「給神的禮物」或「獻給神的東西」或「呈獻給神的貴重物品」。</p></li><li><p>根據上下文，「犧牲」一詞也可以翻譯為「在敬拜中獻上的貴重之物」或「獻給神的特別動物」。</p></li><li><p>「獻祭」的行為可以翻譯為「放棄某些有價值的東西」或「殺死一隻動物並將其獻給神」。</p></li><li><p>「將自己獻上當作活祭」的另一種翻譯是「在你的生活中，將自己完全獻給神，就像動物被獻在祭壇上一樣。」</p></li></ul><p>（另見：<span data-bnType=\"resourceReference\" data-resourceId=\"25447\" data-resourceType=\"UWTranslationWords\">祭壇</span>、<span data-bnType=\"resourceReference\" data-resourceId=\"25560\" data-resourceType=\"UWTranslationWords\">燔祭</span>、<span data-bnType=\"resourceReference\" data-resourceId=\"25683\" data-resourceType=\"UWTranslationWords\">奠祭</span>、<span data-bnType=\"resourceReference\" data-resourceId=\"25728\" data-resourceType=\"UWTranslationWords\">假神</span>、<span data-bnType=\"resourceReference\" data-resourceId=\"25738\" data-resourceType=\"UWTranslationWords\">平安祭</span>、<span data-bnType=\"resourceReference\" data-resourceId=\"25759\" data-resourceType=\"UWTranslationWords\">甘心祭</span>、<span data-bnType=\"resourceReference\" data-resourceId=\"26081\" data-resourceType=\"UWTranslationWords\">平安祭</span>、<span data-bnType=\"resourceReference\" data-resourceId=\"26121\" data-resourceType=\"UWTranslationWords\">祭司</span>、<span data-bnType=\"resourceReference\" data-resourceId=\"26242\" data-resourceType=\"UWTranslationWords\">贖罪祭</span>、<span data-bnType=\"resourceReference\" data-resourceId=\"26357\" data-resourceType=\"UWTranslationWords\">敬拜</span>）</p><h2>參考經文：</h2><ul><li><p><a href=\"https://ref.ly/2Tim4:6\">提摩太後書4:6</a></p></li><li><p><a href=\"https://ref.ly/Acts7:42\">使徒行傳7:42</a></p></li><li><p><a href=\"https://ref.ly/Acts21:25\">使徒行傳21:25</a></p></li><li><p><a href=\"https://ref.ly/Gen4:3-Gen4:5\">創世記4:3–5</a></p></li><li><p><a href=\"https://ref.ly/Jas2:21-Jas2:24\">雅各書2:21–24</a></p></li><li><p><a href=\"https://ref.ly/Mark1:43-Mark1:44\">馬可福音1:43–44</a></p></li><li><p><a href=\"https://ref.ly/Mark14:12\">馬可福音14:12</a></p></li><li><p><a href=\"https://ref.ly/Matt5:23\">馬太福音5:23</a></p></li></ul><h2><span>聖經開卷故事集裡的例子</span>：</h2><ul><li><p><strong>3:14</strong> <span>挪亞離開船後給神築了一座祭壇，用一些可做<strong>燔祭</strong>的動物<strong>獻上</strong>。神因<strong>燔祭</strong>而喜悅，便賜福給挪亞和他的家人。</span></p></li><li><p><strong>5:6</strong> <span>「帶你的獨生兒子以撒，把他殺了獻為<strong>燔祭</strong>。」 亞伯拉罕再次遵從神的話並預備<strong>獻上</strong>他的兒子。</span></p></li><li><p><strong>5:9</strong> <span>神預備那隻公綿羊來代替以撒作為<strong>燔祭</strong></span>。</p></li><li><p><strong>13:9</strong> <span>如果有人違反了神的律例，可以帶一隻動物到會幕裡作為<strong>祭物</strong>獻給神。祭司會殺掉這隻動物並在祭壇上焚燒，<strong>祭物</strong>的血將掩蓋那個人的罪，使他在神的眼裡得以清潔。</span></p></li><li><p><strong>17:6</strong> <span>大衛想建造一座殿，讓以色列百姓可以在這殿裡敬拜神和<strong>獻祭</strong>。</span></p></li><li><p><strong>48:6</strong> <span>耶穌是不同於其他的大祭司，他將自己當作<strong>祭物</strong>獻上，除去世人所有的罪。</span></p></li><li><p><strong>48:8</strong> 但<span>神預備了耶穌作為<strong>祭物</strong>替我們受死</span>。</p></li><li><p><strong>49:11</strong> <span>因為耶穌把自己當成<strong>祭物</strong>，神可以赦免任何罪，甚至是可怕的罪</span>。</p></li></ul><h2>原文參照：</h2><ul><li><p>史特朗號：H0801，H0817，H0819，H1685，H1890，H1974，H2076，H2077，H2281，H2282，H2398，H2401，H2402，H2403，H2409，H3632，H4394，H4503，H4504，H5066，H5068，H5071，H5257，H5258，H5261，H5262，H5927，H5928，H5930，H6453，H6944，H6999，H7133，H7311，H8002，H8426，H8548，H8573，H8641，G02660，G03340，G10490，G14350，G14940，G23780，G23800，G36460，G43760，G54850</p></li></ul>",
    "associations": {
      "passage": [
        {
          "start_ref": "01031054",
          "start_ref_usfm": "GEN 31:54",
          "end_ref": "01031054",
          "end_ref_usfm": "GEN 31:54"
        },
        {
          "start_ref": "01046001",
          "start_ref_usfm": "GEN 46:1",
          "end_ref": "01046001",
          "end_ref_usfm": "GEN 46:1"
        },
        {
          "start_ref": "02003018",
          "start_ref_usfm": "EXO 3:18",
          "end_ref": "02003018",
          "end_ref_usfm": "EXO 3:18"
        },
        {
          "start_ref": "02005003",
          "start_ref_usfm": "EXO 5:3",
          "end_ref": "02005003",
          "end_ref_usfm": "EXO 5:3"
        },
        {
          "start_ref": "02005008",
          "start_ref_usfm": "EXO 5:8",
          "end_ref": "02005008",
          "end_ref_usfm": "EXO 5:8"
        },
        {
          "start_ref": "02005017",
          "start_ref_usfm": "EXO 5:17",
          "end_ref": "02005017",
          "end_ref_usfm": "EXO 5:17"
        },
        {
          "start_ref": "02008008",
          "start_ref_usfm": "EXO 8:8",
          "end_ref": "02008008",
          "end_ref_usfm": "EXO 8:8"
        },
        {
          "start_ref": "02008025",
          "start_ref_usfm": "EXO 8:25",
          "end_ref": "02008025",
          "end_ref_usfm": "EXO 8:25"
        },
        {
          "start_ref": "02008026",
          "start_ref_usfm": "EXO 8:26",
          "end_ref": "02008026",
          "end_ref_usfm": "EXO 8:26"
        },
        {
          "start_ref": "02008027",
          "start_ref_usfm": "EXO 8:27",
          "end_ref": "02008027",
          "end_ref_usfm": "EXO 8:27"
        },
        {
          "start_ref": "02008028",
          "start_ref_usfm": "EXO 8:28",
          "end_ref": "02008028",
          "end_ref_usfm": "EXO 8:28"
        },
        {
          "start_ref": "02008029",
          "start_ref_usfm": "EXO 8:29",
          "end_ref": "02008029",
          "end_ref_usfm": "EXO 8:29"
        },
        {
          "start_ref": "02010025",
          "start_ref_usfm": "EXO 10:25",
          "end_ref": "02010025",
          "end_ref_usfm": "EXO 10:25"
        },
        {
          "start_ref": "02012027",
          "start_ref_usfm": "EXO 12:27",
          "end_ref": "02012027",
          "end_ref_usfm": "EXO 12:27"
        },
        {
          "start_ref": "02013015",
          "start_ref_usfm": "EXO 13:15",
          "end_ref": "02013015",
          "end_ref_usfm": "EXO 13:15"
        },
        {
          "start_ref": "02018012",
          "start_ref_usfm": "EXO 18:12",
          "end_ref": "02018012",
          "end_ref_usfm": "EXO 18:12"
        },
        {
          "start_ref": "02020024",
          "start_ref_usfm": "EXO 20:24",
          "end_ref": "02020024",
          "end_ref_usfm": "EXO 20:24"
        },
        {
          "start_ref": "02022020",
          "start_ref_usfm": "EXO 22:20",
          "end_ref": "02022020",
          "end_ref_usfm": "EXO 22:20"
        },
        {
          "start_ref": "02023018",
          "start_ref_usfm": "EXO 23:18",
          "end_ref": "02023018",
          "end_ref_usfm": "EXO 23:18"
        },
        {
          "start_ref": "02024005",
          "start_ref_usfm": "EXO 24:5",
          "end_ref": "02024005",
          "end_ref_usfm": "EXO 24:5"
        },
        {
          "start_ref": "02029018",
          "start_ref_usfm": "EXO 29:18",
          "end_ref": "02029018",
          "end_ref_usfm": "EXO 29:18"
        },
        {
          "start_ref": "02029024",
          "start_ref_usfm": "EXO 29:24",
          "end_ref": "02029024",
          "end_ref_usfm": "EXO 29:24"
        },
        {
          "start_ref": "02029025",
          "start_ref_usfm": "EXO 29:25",
          "end_ref": "02029025",
          "end_ref_usfm": "EXO 29:25"
        },
        {
          "start_ref": "02029026",
          "start_ref_usfm": "EXO 29:26",
          "end_ref": "02029026",
          "end_ref_usfm": "EXO 29:26"
        },
        {
          "start_ref": "02029027",
          "start_ref_usfm": "EXO 29:27",
          "end_ref": "02029027",
          "end_ref_usfm": "EXO 29:27"
        },
        {
          "start_ref": "02029028",
          "start_ref_usfm": "EXO 29:28",
          "end_ref": "02029028",
          "end_ref_usfm": "EXO 29:28"
        },
        {
          "start_ref": "02029036",
          "start_ref_usfm": "EXO 29:36",
          "end_ref": "02029036",
          "end_ref_usfm": "EXO 29:36"
        },
        {
          "start_ref": "02029038",
          "start_ref_usfm": "EXO 29:38",
          "end_ref": "02029038",
          "end_ref_usfm": "EXO 29:38"
        },
        {
          "start_ref": "02029039",
          "start_ref_usfm": "EXO 29:39",
          "end_ref": "02029039",
          "end_ref_usfm": "EXO 29:39"
        },
        {
          "start_ref": "02029041",
          "start_ref_usfm": "EXO 29:41",
          "end_ref": "02029041",
          "end_ref_usfm": "EXO 29:41"
        },
        {
          "start_ref": "02030009",
          "start_ref_usfm": "EXO 30:9",
          "end_ref": "02030009",
          "end_ref_usfm": "EXO 30:9"
        },
        {
          "start_ref": "02030013",
          "start_ref_usfm": "EXO 30:13",
          "end_ref": "02030013",
          "end_ref_usfm": "EXO 30:13"
        },
        {
          "start_ref": "02030014",
          "start_ref_usfm": "EXO 30:14",
          "end_ref": "02030014",
          "end_ref_usfm": "EXO 30:14"
        },
        {
          "start_ref": "02030020",
          "start_ref_usfm": "EXO 30:20",
          "end_ref": "02030020",
          "end_ref_usfm": "EXO 30:20"
        },
        {
          "start_ref": "02032008",
          "start_ref_usfm": "EXO 32:8",
          "end_ref": "02032008",
          "end_ref_usfm": "EXO 32:8"
        },
        {
          "start_ref": "02034015",
          "start_ref_usfm": "EXO 34:15",
          "end_ref": "02034015",
          "end_ref_usfm": "EXO 34:15"
        },
        {
          "start_ref": "02034025",
          "start_ref_usfm": "EXO 34:25",
          "end_ref": "02034025",
          "end_ref_usfm": "EXO 34:25"
        },
        {
          "start_ref": "02035005",
          "start_ref_usfm": "EXO 35:5",
          "end_ref": "02035005",
          "end_ref_usfm": "EXO 35:5"
        },
        {
          "start_ref": "02035022",
          "start_ref_usfm": "EXO 35:22",
          "end_ref": "02035022",
          "end_ref_usfm": "EXO 35:22"
        },
        {
          "start_ref": "15004002",
          "start_ref_usfm": "EZR 4:2",
          "end_ref": "15004002",
          "end_ref_usfm": "EZR 4:2"
        },
        {
          "start_ref": "15006003",
          "start_ref_usfm": "EZR 6:3",
          "end_ref": "15006003",
          "end_ref_usfm": "EZR 6:3"
        },
        {
          "start_ref": "15006010",
          "start_ref_usfm": "EZR 6:10",
          "end_ref": "15006010",
          "end_ref_usfm": "EZR 6:10"
        },
        {
          "start_ref": "16004002",
          "start_ref_usfm": "NEH 4:2",
          "end_ref": "16004002",
          "end_ref_usfm": "NEH 4:2"
        },
        {
          "start_ref": "16012043",
          "start_ref_usfm": "NEH 12:43",
          "end_ref": "16012043",
          "end_ref_usfm": "NEH 12:43"
        },
        {
          "start_ref": "20007014",
          "start_ref_usfm": "PRO 7:14",
          "end_ref": "20007014",
          "end_ref_usfm": "PRO 7:14"
        },
        {
          "start_ref": "20015008",
          "start_ref_usfm": "PRO 15:8",
          "end_ref": "20015008",
          "end_ref_usfm": "PRO 15:8"
        },
        {
          "start_ref": "20017001",
          "start_ref_usfm": "PRO 17:1",
          "end_ref": "20017001",
          "end_ref_usfm": "PRO 17:1"
        },
        {
          "start_ref": "20021027",
          "start_ref_usfm": "PRO 21:27",
          "end_ref": "20021027",
          "end_ref_usfm": "PRO 21:27"
        },
        {
          "start_ref": "32001016",
          "start_ref_usfm": "JON 1:16",
          "end_ref": "32001016",
          "end_ref_usfm": "JON 1:16"
        },
        {
          "start_ref": "32002009",
          "start_ref_usfm": "JON 2:9",
          "end_ref": "32002009",
          "end_ref_usfm": "JON 2:9"
        },
        {
          "start_ref": "36001007",
          "start_ref_usfm": "ZEP 1:7",
          "end_ref": "36001007",
          "end_ref_usfm": "ZEP 1:7"
        },
        {
          "start_ref": "36001008",
          "start_ref_usfm": "ZEP 1:8",
          "end_ref": "36001008",
          "end_ref_usfm": "ZEP 1:8"
        },
        {
          "start_ref": "40005023",
          "start_ref_usfm": "MAT 5:23",
          "end_ref": "40005023",
          "end_ref_usfm": "MAT 5:23"
        },
        {
          "start_ref": "40009013",
          "start_ref_usfm": "MAT 9:13",
          "end_ref": "40009013",
          "end_ref_usfm": "MAT 9:13"
        },
        {
          "start_ref": "40012007",
          "start_ref_usfm": "MAT 12:7",
          "end_ref": "40012007",
          "end_ref_usfm": "MAT 12:7"
        },
        {
          "start_ref": "41012033",
          "start_ref_usfm": "MRK 12:33",
          "end_ref": "41012033",
          "end_ref_usfm": "MRK 12:33"
        },
        {
          "start_ref": "41014012",
          "start_ref_usfm": "MRK 14:12",
          "end_ref": "41014012",
          "end_ref_usfm": "MRK 14:12"
        },
        {
          "start_ref": "42002024",
          "start_ref_usfm": "LUK 2:24",
          "end_ref": "42002024",
          "end_ref_usfm": "LUK 2:24"
        },
        {
          "start_ref": "42013001",
          "start_ref_usfm": "LUK 13:1",
          "end_ref": "42013001",
          "end_ref_usfm": "LUK 13:1"
        },
        {
          "start_ref": "44007041",
          "start_ref_usfm": "ACT 7:41",
          "end_ref": "44007041",
          "end_ref_usfm": "ACT 7:41"
        },
        {
          "start_ref": "44007042",
          "start_ref_usfm": "ACT 7:42",
          "end_ref": "44007042",
          "end_ref_usfm": "ACT 7:42"
        },
        {
          "start_ref": "44014013",
          "start_ref_usfm": "ACT 14:13",
          "end_ref": "44014013",
          "end_ref_usfm": "ACT 14:13"
        },
        {
          "start_ref": "44014018",
          "start_ref_usfm": "ACT 14:18",
          "end_ref": "44014018",
          "end_ref_usfm": "ACT 14:18"
        },
        {
          "start_ref": "44021025",
          "start_ref_usfm": "ACT 21:25",
          "end_ref": "44021025",
          "end_ref_usfm": "ACT 21:25"
        },
        {
          "start_ref": "44021026",
          "start_ref_usfm": "ACT 21:26",
          "end_ref": "44021026",
          "end_ref_usfm": "ACT 21:26"
        },
        {
          "start_ref": "44024017",
          "start_ref_usfm": "ACT 24:17",
          "end_ref": "44024017",
          "end_ref_usfm": "ACT 24:17"
        },
        {
          "start_ref": "45012001",
          "start_ref_usfm": "ROM 12:1",
          "end_ref": "45012001",
          "end_ref_usfm": "ROM 12:1"
        },
        {
          "start_ref": "45015016",
          "start_ref_usfm": "ROM 15:16",
          "end_ref": "45015016",
          "end_ref_usfm": "ROM 15:16"
        },
        {
          "start_ref": "46005007",
          "start_ref_usfm": "1CO 5:7",
          "end_ref": "46005007",
          "end_ref_usfm": "1CO 5:7"
        },
        {
          "start_ref": "46010018",
          "start_ref_usfm": "1CO 10:18",
          "end_ref": "46010018",
          "end_ref_usfm": "1CO 10:18"
        },
        {
          "start_ref": "46010020",
          "start_ref_usfm": "1CO 10:20",
          "end_ref": "46010020",
          "end_ref_usfm": "1CO 10:20"
        },
        {
          "start_ref": "49005002",
          "start_ref_usfm": "EPH 5:2",
          "end_ref": "49005002",
          "end_ref_usfm": "EPH 5:2"
        },
        {
          "start_ref": "50002017",
          "start_ref_usfm": "PHP 2:17",
          "end_ref": "50002017",
          "end_ref_usfm": "PHP 2:17"
        },
        {
          "start_ref": "50004018",
          "start_ref_usfm": "PHP 4:18",
          "end_ref": "50004018",
          "end_ref_usfm": "PHP 4:18"
        },
        {
          "start_ref": "55004006",
          "start_ref_usfm": "2TI 4:6",
          "end_ref": "55004006",
          "end_ref_usfm": "2TI 4:6"
        },
        {
          "start_ref": "58005001",
          "start_ref_usfm": "HEB 5:1",
          "end_ref": "58005001",
          "end_ref_usfm": "HEB 5:1"
        },
        {
          "start_ref": "58007027",
          "start_ref_usfm": "HEB 7:27",
          "end_ref": "58007027",
          "end_ref_usfm": "HEB 7:27"
        },
        {
          "start_ref": "58008003",
          "start_ref_usfm": "HEB 8:3",
          "end_ref": "58008003",
          "end_ref_usfm": "HEB 8:3"
        },
        {
          "start_ref": "58009009",
          "start_ref_usfm": "HEB 9:9",
          "end_ref": "58009009",
          "end_ref_usfm": "HEB 9:9"
        },
        {
          "start_ref": "58009023",
          "start_ref_usfm": "HEB 9:23",
          "end_ref": "58009023",
          "end_ref_usfm": "HEB 9:23"
        },
        {
          "start_ref": "58009026",
          "start_ref_usfm": "HEB 9:26",
          "end_ref": "58009026",
          "end_ref_usfm": "HEB 9:26"
        },
        {
          "start_ref": "58010001",
          "start_ref_usfm": "HEB 10:1",
          "end_ref": "58010001",
          "end_ref_usfm": "HEB 10:1"
        },
        {
          "start_ref": "58010005",
          "start_ref_usfm": "HEB 10:5",
          "end_ref": "58010005",
          "end_ref_usfm": "HEB 10:5"
        },
        {
          "start_ref": "58010008",
          "start_ref_usfm": "HEB 10:8",
          "end_ref": "58010008",
          "end_ref_usfm": "HEB 10:8"
        },
        {
          "start_ref": "58010010",
          "start_ref_usfm": "HEB 10:10",
          "end_ref": "58010010",
          "end_ref_usfm": "HEB 10:10"
        },
        {
          "start_ref": "58010011",
          "start_ref_usfm": "HEB 10:11",
          "end_ref": "58010011",
          "end_ref_usfm": "HEB 10:11"
        },
        {
          "start_ref": "58010012",
          "start_ref_usfm": "HEB 10:12",
          "end_ref": "58010012",
          "end_ref_usfm": "HEB 10:12"
        },
        {
          "start_ref": "58010014",
          "start_ref_usfm": "HEB 10:14",
          "end_ref": "58010014",
          "end_ref_usfm": "HEB 10:14"
        },
        {
          "start_ref": "58010018",
          "start_ref_usfm": "HEB 10:18",
          "end_ref": "58010018",
          "end_ref_usfm": "HEB 10:18"
        },
        {
          "start_ref": "58010026",
          "start_ref_usfm": "HEB 10:26",
          "end_ref": "58010026",
          "end_ref_usfm": "HEB 10:26"
        },
        {
          "start_ref": "58011004",
          "start_ref_usfm": "HEB 11:4",
          "end_ref": "58011004",
          "end_ref_usfm": "HEB 11:4"
        },
        {
          "start_ref": "58013015",
          "start_ref_usfm": "HEB 13:15",
          "end_ref": "58013015",
          "end_ref_usfm": "HEB 13:15"
        },
        {
          "start_ref": "58013016",
          "start_ref_usfm": "HEB 13:16",
          "end_ref": "58013016",
          "end_ref_usfm": "HEB 13:16"
        },
        {
          "start_ref": "60002005",
          "start_ref_usfm": "1PE 2:5",
          "end_ref": "60002005",
          "end_ref_usfm": "1PE 2:5"
        },
        {
          "start_ref": "59002021",
          "start_ref_usfm": "JAS 2:21",
          "end_ref": "59002024",
          "end_ref_usfm": "JAS 2:24"
        },
        {
          "start_ref": "01004003",
          "start_ref_usfm": "GEN 4:3",
          "end_ref": "01004005",
          "end_ref_usfm": "GEN 4:5"
        },
        {
          "start_ref": "41001043",
          "start_ref_usfm": "MRK 1:43",
          "end_ref": "41001044",
          "end_ref_usfm": "MRK 1:44"
        }
      ],
      "resource": [
        {
          "reference_id": 25447,
          "content_id": 390388,
          "resource_code": "UWTranslationWords",
          "label": "祭壇",
          "language": "zht"
        },
        {
          "reference_id": 25560,
          "content_id": 390500,
          "resource_code": "UWTranslationWords",
          "label": "燔祭",
          "language": "zht"
        },
        {
          "reference_id": 25683,
          "content_id": 390620,
          "resource_code": "UWTranslationWords",
          "label": "奠祭",
          "language": "zht"
        },
        {
          "reference_id": 25728,
          "content_id": 390662,
          "resource_code": "UWTranslationWords",
          "label": "假神",
          "language": "zht"
        },
        {
          "reference_id": 25738,
          "content_id": 390672,
          "resource_code": "UWTranslationWords",
          "label": "平安祭",
          "language": "zht"
        },
        {
          "reference_id": 25759,
          "content_id": 390693,
          "resource_code": "UWTranslationWords",
          "label": "甘心祭",
          "language": "zht"
        },
        {
          "reference_id": 26081,
          "content_id": 391006,
          "resource_code": "UWTranslationWords",
          "label": "平安祭",
          "language": "zht"
        },
        {
          "reference_id": 26121,
          "content_id": 391045,
          "resource_code": "UWTranslationWords",
          "label": "祭司",
          "language": "zht"
        },
        {
          "reference_id": 26242,
          "content_id": 391164,
          "resource_code": "UWTranslationWords",
          "label": "贖罪祭",
          "language": "zht"
        },
        {
          "reference_id": 26357,
          "content_id": 391277,
          "resource_code": "UWTranslationWords",
          "label": "敬拜",
          "language": "zht"
        }
      ]
    }
  }
]