[
  {
    "content_id": 676032,
    "reference_id": 26006,
    "title": "Laut",
    "media_type": "Text",
    "index_reference": "laut",
    "language": "ind",
    "content": "<h1>laut, Laut Besar, laut barat, Laut Mediterania</h1><h2>Fakta:</h2><p>Dalam Alkitab, “Laut Besar” atau “laut barat” mengacu pada apa yang sekarang disebut “Laut Mediterania” atau &quot;Laut Tengah,&quot; yang merupakan perairan terbesar yang dikenal orang-orang pada zaman Alkitab.</p><ul><li><p>Laut Mediterania berbatasan dengan: Israel (timur), Eropa (utara dan barat), dan Afrika (selatan).</p></li><li><p>Laut ini pada zaman dahulu sangat penting untuk perdagangan dan perjalanan karena berbatasan dengan banyak negara. Kota-kota dan kelompok masyarakat yang terletak di pesisir laut ini sangat makmur karena mudahnya mengakses barang-barang dari negara lain dengan menggunakan kapal.</p></li><li><p>Karena Laut Besar terletak di sebelah barat Israel, kadang-kadang disebut sebagai “laut barat”.</p></li></ul><p>(Saran terjemahan: Cara Menerjemahkan Nama)</p><p>(Lihat juga: <span data-bnType=\"resourceReference\" data-resourceId=\"25879\" data-resourceType=\"UWTranslationWords\">Israel</span>, <span data-bnType=\"resourceReference\" data-resourceId=\"26083\" data-resourceType=\"UWTranslationWords\">people group</span>, <span data-bnType=\"resourceReference\" data-resourceId=\"26131\" data-resourceType=\"UWTranslationWords\">prosper</span>)</p><h2>Referensi Alkitab:</h2><ul><li><p><a href=\"https://ref.ly/Ezek47:15-Ezek47:17\">Yehezkiel 47:15–17</a></p></li><li><p><a href=\"https://ref.ly/Ezek47:18-Ezek47:20\">Yehezkiel 47:18–20</a></p></li><li><p><a href=\"https://ref.ly/Josh15:3-Josh15:4\">Yosua 15:3–4</a></p></li><li><p><a href=\"https://ref.ly/Num13:27-Num13:29\">Bilangan 13:27–29</a></p></li></ul><h2>Data Kata:</h2><ul><li><p>Strong’s: H0314, H1419, H3220</p></li></ul>",
    "associations": {
      "passage": [
        {
          "start_ref": "02023031",
          "start_ref_usfm": "EXO 23:31",
          "end_ref": "02023031",
          "end_ref_usfm": "EXO 23:31"
        },
        {
          "start_ref": "44010006",
          "start_ref_usfm": "ACT 10:6",
          "end_ref": "44010006",
          "end_ref_usfm": "ACT 10:6"
        },
        {
          "start_ref": "44010032",
          "start_ref_usfm": "ACT 10:32",
          "end_ref": "44010032",
          "end_ref_usfm": "ACT 10:32"
        },
        {
          "start_ref": "44017014",
          "start_ref_usfm": "ACT 17:14",
          "end_ref": "44017014",
          "end_ref_usfm": "ACT 17:14"
        },
        {
          "start_ref": "44027030",
          "start_ref_usfm": "ACT 27:30",
          "end_ref": "44027030",
          "end_ref_usfm": "ACT 27:30"
        },
        {
          "start_ref": "44027038",
          "start_ref_usfm": "ACT 27:38",
          "end_ref": "44027038",
          "end_ref_usfm": "ACT 27:38"
        },
        {
          "start_ref": "44027040",
          "start_ref_usfm": "ACT 27:40",
          "end_ref": "44027040",
          "end_ref_usfm": "ACT 27:40"
        },
        {
          "start_ref": "44028004",
          "start_ref_usfm": "ACT 28:4",
          "end_ref": "44028004",
          "end_ref_usfm": "ACT 28:4"
        },
        {
          "start_ref": "06015003",
          "start_ref_usfm": "JOS 15:3",
          "end_ref": "06015004",
          "end_ref_usfm": "JOS 15:4"
        },
        {
          "start_ref": "26047015",
          "start_ref_usfm": "EZK 47:15",
          "end_ref": "26047017",
          "end_ref_usfm": "EZK 47:17"
        },
        {
          "start_ref": "04013027",
          "start_ref_usfm": "NUM 13:27",
          "end_ref": "04013029",
          "end_ref_usfm": "NUM 13:29"
        },
        {
          "start_ref": "26047018",
          "start_ref_usfm": "EZK 47:18",
          "end_ref": "26047020",
          "end_ref_usfm": "EZK 47:20"
        }
      ],
      "resource": [
        {
          "reference_id": 25879,
          "content_id": 675931,
          "resource_code": "UWTranslationWords",
          "label": "Israel",
          "language": "ind"
        },
        {
          "reference_id": 26083,
          "content_id": 676090,
          "resource_code": "UWTranslationWords",
          "label": "Bangsa",
          "language": "ind"
        },
        {
          "reference_id": 26131,
          "content_id": 676112,
          "resource_code": "UWTranslationWords",
          "label": "Sejahtera",
          "language": "ind"
        }
      ]
    }
  }
]